{"Name":"ngcutfs3_208","Objects":[{"Length":100,"Height":100,"Stock":null,"Cost":10000}],"Items":[{"Length":2,"Height":49,"Demand":0,"DemandMax":4,"Value":196},{"Length":37,"Height":29,"Demand":0,"DemandMax":4,"Value":2146},{"Length":6,"Height":48,"Demand":0,"DemandMax":4,"Value":864},{"Length":46,"Height":8,"Demand":0,"DemandMax":4,"Value":736},{"Length":30,"Height":39,"Demand":0,"DemandMax":8,"Value":1170},{"Length":2,"Height":47,"Demand":0,"DemandMax":4,"Value":188},{"Length":35,"Height":43,"Demand":0,"DemandMax":4,"Value":3010},{"Length":6,"Height":31,"Demand":0,"DemandMax":4,"Value":558},{"Length":98,"Height":33,"Demand":0,"DemandMax":4,"Value":6468},{"Length":44,"Height":33,"Demand":0,"DemandMax":4,"Value":1452},{"Length":85,"Height":24,"Demand":0,"DemandMax":4,"Value":2040},{"Length":9,"Height":91,"Demand":0,"DemandMax":4,"Value":2457},{"Length":40,"Height":19,"Demand":0,"DemandMax":4,"Value":760},{"Length":5,"Height":2,"Demand":0,"DemandMax":4,"Value":30},{"Length":80,"Height":75,"Demand":0,"DemandMax":4,"Value":12000},{"Length":35,"Height":27,"Demand":0,"DemandMax":4,"Value":945},{"Length":20,"Height":30,"Demand":0,"DemandMax":4,"Value":600},{"Length":95,"Height":96,"Demand":0,"DemandMax":4,"Value":27360},{"Length":24,"Height":45,"Demand":0,"DemandMax":4,"Value":2160},{"Length":33,"Height":50,"Demand":0,"DemandMax":8,"Value":1650},{"Length":7,"Height":87,"Demand":0,"DemandMax":4,"Value":609},{"Length":41,"Height":44,"Demand":0,"DemandMax":4,"Value":3608},{"Length":30,"Height":39,"Demand":0,"DemandMax":4,"Value":2340},{"Length":49,"Height":10,"Demand":0,"DemandMax":4,"Value":1470},{"Length":23,"Height":76,"Demand":0,"DemandMax":4,"Value":5244},{"Length":38,"Height":9,"Demand":0,"DemandMax":4,"Value":342},{"Length":52,"Height":91,"Demand":0,"DemandMax":4,"Value":4732},{"Length":26,"Height":9,"Demand":0,"DemandMax":4,"Value":234},{"Length":26,"Height":43,"Demand":0,"DemandMax":4,"Value":1118},{"Length":23,"Height":31,"Demand":0,"DemandMax":4,"Value":713},{"Length":21,"Height":36,"Demand":0,"DemandMax":4,"Value":1512},{"Length":15,"Height":2,"Demand":0,"DemandMax":4,"Value":60},{"Length":89,"Height":60,"Demand":0,"DemandMax":4,"Value":5340},{"Length":23,"Height":11,"Demand":0,"DemandMax":4,"Value":253},{"Length":22,"Height":14,"Demand":0,"DemandMax":4,"Value":924},{"Length":6,"Height":20,"Demand":0,"DemandMax":4,"Value":240},{"Length":8,"Height":7,"Demand":0,"DemandMax":4,"Value":56},{"Length":91,"Height":45,"Demand":0,"DemandMax":4,"Value":4095},{"Length":93,"Height":62,"Demand":0,"DemandMax":4,"Value":11532},{"Length":44,"Height":4,"Demand":0,"DemandMax":4,"Value":352},{"Length":43,"Height":15,"Demand":0,"DemandMax":4,"Value":645},{"Length":15,"Height":48,"Demand":0,"DemandMax":4,"Value":1440},{"Length":22,"Height":15,"Demand":0,"DemandMax":4,"Value":990},{"Length":76,"Height":32,"Demand":0,"DemandMax":4,"Value":2432},{"Length":55,"Height":90,"Demand":0,"DemandMax":4,"Value":9900},{"Length":14,"Height":50,"Demand":0,"DemandMax":4,"Value":700},{"Length":23,"Height":24,"Demand":0,"DemandMax":4,"Value":1656},{"Length":23,"Height":19,"Demand":0,"DemandMax":4,"Value":437},{"Length":48,"Height":39,"Demand":0,"DemandMax":8,"Value":5616},{"Length":17,"Height":21,"Demand":0,"DemandMax":4,"Value":1071},{"Length":3,"Height":50,"Demand":0,"DemandMax":4,"Value":450},{"Length":40,"Height":3,"Demand":0,"DemandMax":4,"Value":360},{"Length":74,"Height":82,"Demand":0,"DemandMax":4,"Value":18204},{"Length":32,"Height":2,"Demand":0,"DemandMax":4,"Value":192},{"Length":7,"Height":20,"Demand":0,"DemandMax":4,"Value":420},{"Length":49,"Height":31,"Demand":0,"DemandMax":4,"Value":3038},{"Length":88,"Height":34,"Demand":0,"DemandMax":4,"Value":8976},{"Length":29,"Height":35,"Demand":0,"DemandMax":4,"Value":2030},{"Length":53,"Height":68,"Demand":0,"DemandMax":4,"Value":3604},{"Length":78,"Height":13,"Demand":0,"DemandMax":4,"Value":2028},{"Length":14,"Height":42,"Demand":0,"DemandMax":4,"Value":588},{"Length":25,"Height":28,"Demand":0,"DemandMax":8,"Value":2100},{"Length":13,"Height":12,"Demand":0,"DemandMax":8,"Value":156},{"Length":18,"Height":31,"Demand":0,"DemandMax":4,"Value":1674},{"Length":23,"Height":41,"Demand":0,"DemandMax":4,"Value":943},{"Length":16,"Height":36,"Demand":0,"DemandMax":4,"Value":1728},{"Length":2,"Height":31,"Demand":0,"DemandMax":4,"Value":62},{"Length":3,"Height":14,"Demand":0,"DemandMax":4,"Value":84},{"Length":42,"Height":17,"Demand":0,"DemandMax":4,"Value":714},{"Length":3,"Height":6,"Demand":0,"DemandMax":4,"Value":36},{"Length":31,"Height":25,"Demand":0,"DemandMax":4,"Value":1550},{"Length":47,"Height":34,"Demand":0,"DemandMax":4,"Value":1598},{"Length":2,"Height":14,"Demand":0,"DemandMax":4,"Value":28},{"Length":29,"Height":2,"Demand":0,"DemandMax":4,"Value":116},{"Length":43,"Height":48,"Demand":0,"DemandMax":4,"Value":6192},{"Length":41,"Height":33,"Demand":0,"DemandMax":4,"Value":4059},{"Length":43,"Height":17,"Demand":0,"DemandMax":4,"Value":1462},{"Length":36,"Height":27,"Demand":0,"DemandMax":4,"Value":1944},{"Length":50,"Height":15,"Demand":0,"DemandMax":4,"Value":750},{"Length":78,"Height":34,"Demand":0,"DemandMax":4,"Value":5304},{"Length":14,"Height":35,"Demand":0,"DemandMax":4,"Value":490},{"Length":12,"Height":30,"Demand":0,"DemandMax":4,"Value":360},{"Length":52,"Height":88,"Demand":0,"DemandMax":4,"Value":13728},{"Length":88,"Height":88,"Demand":0,"DemandMax":4,"Value":7744},{"Length":22,"Height":2,"Demand":0,"DemandMax":4,"Value":132},{"Length":37,"Height":13,"Demand":0,"DemandMax":4,"Value":1443},{"Length":91,"Height":13,"Demand":0,"DemandMax":4,"Value":1183},{"Length":16,"Height":6,"Demand":0,"DemandMax":4,"Value":192},{"Length":45,"Height":24,"Demand":0,"DemandMax":4,"Value":3240},{"Length":34,"Height":45,"Demand":0,"DemandMax":4,"Value":3060},{"Length":23,"Height":87,"Demand":0,"DemandMax":4,"Value":4002},{"Length":82,"Height":43,"Demand":0,"DemandMax":4,"Value":10578},{"Length":32,"Height":14,"Demand":0,"DemandMax":4,"Value":448},{"Length":40,"Height":82,"Demand":0,"DemandMax":4,"Value":9840},{"Length":13,"Height":14,"Demand":0,"DemandMax":4,"Value":182},{"Length":24,"Height":31,"Demand":0,"DemandMax":4,"Value":1488},{"Length":38,"Height":21,"Demand":0,"DemandMax":4,"Value":2394},{"Length":20,"Height":29,"Demand":0,"DemandMax":4,"Value":1160},{"Length":9,"Height":2,"Demand":0,"DemandMax":4,"Value":18},{"Length":33,"Height":16,"Demand":0,"DemandMax":4,"Value":1584},{"Length":79,"Height":40,"Demand":0,"DemandMax":8,"Value":3160},{"Length":33,"Height":12,"Demand":0,"DemandMax":4,"Value":1188},{"Length":96,"Height":43,"Demand":0,"DemandMax":4,"Value":8256},{"Length":30,"Height":38,"Demand":0,"DemandMax":8,"Value":3420},{"Length":81,"Height":18,"Demand":0,"DemandMax":4,"Value":1458},{"Length":4,"Height":19,"Demand":0,"DemandMax":4,"Value":228},{"Length":19,"Height":98,"Demand":0,"DemandMax":4,"Value":5586},{"Length":15,"Height":81,"Demand":0,"DemandMax":4,"Value":2430},{"Length":7,"Height":41,"Demand":0,"DemandMax":4,"Value":287},{"Length":50,"Height":34,"Demand":0,"DemandMax":4,"Value":1700},{"Length":42,"Height":86,"Demand":0,"DemandMax":4,"Value":7224},{"Length":44,"Height":37,"Demand":0,"DemandMax":4,"Value":4884},{"Length":4,"Height":4,"Demand":0,"DemandMax":4,"Value":32},{"Length":94,"Height":74,"Demand":0,"DemandMax":4,"Value":20868},{"Length":14,"Height":29,"Demand":0,"DemandMax":4,"Value":406},{"Length":74,"Height":85,"Demand":0,"DemandMax":4,"Value":6290},{"Length":30,"Height":49,"Demand":0,"DemandMax":4,"Value":4410},{"Length":38,"Height":33,"Demand":0,"DemandMax":4,"Value":1254},{"Length":42,"Height":14,"Demand":0,"DemandMax":4,"Value":1176},{"Length":37,"Height":7,"Demand":0,"DemandMax":4,"Value":518},{"Length":8,"Height":29,"Demand":0,"DemandMax":4,"Value":696},{"Length":36,"Height":85,"Demand":0,"DemandMax":4,"Value":3060},{"Length":48,"Height":31,"Demand":0,"DemandMax":4,"Value":2976},{"Length":18,"Height":34,"Demand":0,"DemandMax":4,"Value":1836},{"Length":24,"Height":29,"Demand":0,"DemandMax":8,"Value":696},{"Length":88,"Height":98,"Demand":0,"DemandMax":4,"Value":8624},{"Length":13,"Height":44,"Demand":0,"DemandMax":4,"Value":1716},{"Length":45,"Height":36,"Demand":0,"DemandMax":8,"Value":1620},{"Length":10,"Height":4,"Demand":0,"DemandMax":4,"Value":80},{"Length":43,"Height":27,"Demand":0,"DemandMax":4,"Value":1161},{"Length":60,"Height":62,"Demand":0,"DemandMax":4,"Value":7440},{"Length":30,"Height":33,"Demand":0,"DemandMax":4,"Value":2970},{"Length":34,"Height":21,"Demand":0,"DemandMax":4,"Value":714},{"Length":8,"Height":11,"Demand":0,"DemandMax":4,"Value":88},{"Length":2,"Height":15,"Demand":0,"DemandMax":4,"Value":90},{"Length":45,"Height":4,"Demand":0,"DemandMax":4,"Value":360},{"Length":24,"Height":39,"Demand":0,"DemandMax":4,"Value":936},{"Length":42,"Height":43,"Demand":0,"DemandMax":4,"Value":5418},{"Length":43,"Height":77,"Demand":0,"DemandMax":4,"Value":6622},{"Length":21,"Height":35,"Demand":0,"DemandMax":4,"Value":735},{"Length":45,"Height":9,"Demand":0,"DemandMax":4,"Value":405},{"Length":43,"Height":8,"Demand":0,"DemandMax":4,"Value":344},{"Length":19,"Height":21,"Demand":0,"DemandMax":4,"Value":1197},{"Length":90,"Height":99,"Demand":0,"DemandMax":4,"Value":17820},{"Length":14,"Height":35,"Demand":0,"DemandMax":4,"Value":1470},{"Length":7,"Height":18,"Demand":0,"DemandMax":8,"Value":378},{"Length":19,"Height":13,"Demand":0,"DemandMax":8,"Value":494},{"Length":33,"Height":84,"Demand":0,"DemandMax":4,"Value":5544},{"Length":82,"Height":87,"Demand":0,"DemandMax":4,"Value":7134},{"Length":11,"Height":34,"Demand":0,"DemandMax":4,"Value":748},{"Length":28,"Height":29,"Demand":0,"DemandMax":4,"Value":2436},{"Length":31,"Height":2,"Demand":0,"DemandMax":4,"Value":124},{"Length":46,"Height":45,"Demand":0,"DemandMax":4,"Value":6210},{"Length":73,"Height":52,"Demand":0,"DemandMax":4,"Value":7592},{"Length":38,"Height":35,"Demand":0,"DemandMax":4,"Value":3990},{"Length":33,"Height":18,"Demand":0,"DemandMax":4,"Value":1188},{"Length":32,"Height":12,"Demand":0,"DemandMax":4,"Value":384},{"Length":6,"Height":91,"Demand":0,"DemandMax":4,"Value":546},{"Length":47,"Height":8,"Demand":0,"DemandMax":4,"Value":376},{"Length":40,"Height":77,"Demand":0,"DemandMax":4,"Value":9240},{"Length":7,"Height":43,"Demand":0,"DemandMax":8,"Value":602},{"Length":49,"Height":47,"Demand":0,"DemandMax":4,"Value":2303},{"Length":12,"Height":27,"Demand":0,"DemandMax":4,"Value":972},{"Length":85,"Height":70,"Demand":0,"DemandMax":4,"Value":11900},{"Length":70,"Height":53,"Demand":0,"DemandMax":4,"Value":7420},{"Length":14,"Height":30,"Demand":0,"DemandMax":4,"Value":420},{"Length":2,"Height":34,"Demand":0,"DemandMax":4,"Value":136},{"Length":5,"Height":89,"Demand":0,"DemandMax":4,"Value":890},{"Length":14,"Height":38,"Demand":0,"DemandMax":4,"Value":1064},{"Length":19,"Height":42,"Demand":0,"DemandMax":4,"Value":1596},{"Length":86,"Height":27,"Demand":0,"DemandMax":4,"Value":6966},{"Length":31,"Height":95,"Demand":0,"DemandMax":4,"Value":5890},{"Length":21,"Height":6,"Demand":0,"DemandMax":4,"Value":252},{"Length":100,"Height":14,"Demand":0,"DemandMax":4,"Value":1400},{"Length":36,"Height":36,"Demand":0,"DemandMax":4,"Value":2592},{"Length":46,"Height":28,"Demand":0,"DemandMax":4,"Value":1288},{"Length":28,"Height":27,"Demand":0,"DemandMax":4,"Value":1512},{"Length":14,"Height":42,"Demand":0,"DemandMax":4,"Value":1176},{"Length":14,"Height":27,"Demand":0,"DemandMax":4,"Value":1134},{"Length":26,"Height":44,"Demand":0,"DemandMax":4,"Value":1144},{"Length":30,"Height":19,"Demand":0,"DemandMax":4,"Value":1140},{"Length":9,"Height":92,"Demand":0,"DemandMax":4,"Value":2484},{"Length":3,"Height":20,"Demand":0,"DemandMax":8,"Value":60},{"Length":44,"Height":81,"Demand":0,"DemandMax":4,"Value":7128},{"Length":10,"Height":48,"Demand":0,"DemandMax":4,"Value":960},{"Length":16,"Height":25,"Demand":0,"DemandMax":4,"Value":1200},{"Length":15,"Height":82,"Demand":0,"DemandMax":4,"Value":3690},{"Length":27,"Height":9,"Demand":0,"DemandMax":4,"Value":729},{"Length":47,"Height":22,"Demand":0,"DemandMax":4,"Value":3102},{"Length":32,"Height":9,"Demand":0,"DemandMax":4,"Value":288},{"Length":20,"Height":8,"Demand":0,"DemandMax":4,"Value":480},{"Length":11,"Height":4,"Demand":0,"DemandMax":4,"Value":44},{"Length":2,"Height":10,"Demand":0,"DemandMax":4,"Value":60},{"Length":37,"Height":3,"Demand":0,"DemandMax":4,"Value":333},{"Length":40,"Height":49,"Demand":0,"DemandMax":4,"Value":5880},{"Length":39,"Height":44,"Demand":0,"DemandMax":4,"Value":1716},{"Length":5,"Height":4,"Demand":0,"DemandMax":4,"Value":20},{"Length":92,"Height":8,"Demand":0,"DemandMax":4,"Value":1472},{"Length":83,"Height":56,"Demand":0,"DemandMax":4,"Value":13944},{"Length":49,"Height":27,"Demand":0,"DemandMax":4,"Value":1323},{"Length":19,"Height":26,"Demand":0,"DemandMax":4,"Value":988},{"Length":31,"Height":48,"Demand":0,"DemandMax":4,"Value":1488},{"Length":42,"Height":91,"Demand":0,"DemandMax":4,"Value":3822},{"Length":29,"Height":15,"Demand":0,"DemandMax":4,"Value":870},{"Length":37,"Height":23,"Demand":0,"DemandMax":4,"Value":851},{"Length":20,"Height":42,"Demand":0,"DemandMax":4,"Value":840},{"Length":22,"Height":44,"Demand":0,"DemandMax":4,"Value":1936},{"Length":76,"Height":8,"Demand":0,"DemandMax":4,"Value":608},{"Length":20,"Height":19,"Demand":0,"DemandMax":4,"Value":760},{"Length":82,"Height":55,"Demand":0,"DemandMax":4,"Value":13530},{"Length":100,"Height":32,"Demand":0,"DemandMax":4,"Value":6400},{"Length":2,"Height":49,"Demand":0,"DemandMax":4,"Value":98},{"Length":35,"Height":36,"Demand":0,"DemandMax":4,"Value":2520},{"Length":37,"Height":16,"Demand":0,"DemandMax":4,"Value":592},{"Length":9,"Height":15,"Demand":0,"DemandMax":4,"Value":135},{"Length":35,"Height":50,"Demand":0,"DemandMax":4,"Value":3500},{"Length":48,"Height":22,"Demand":0,"DemandMax":4,"Value":3168},{"Length":27,"Height":48,"Demand":0,"DemandMax":4,"Value":3888},{"Length":27,"Height":29,"Demand":0,"DemandMax":4,"Value":2349},{"Length":7,"Height":81,"Demand":0,"DemandMax":4,"Value":1701},{"Length":42,"Height":20,"Demand":0,"DemandMax":4,"Value":1680},{"Length":14,"Height":81,"Demand":0,"DemandMax":4,"Value":3402},{"Length":9,"Height":89,"Demand":0,"DemandMax":4,"Value":801},{"Length":30,"Height":7,"Demand":0,"DemandMax":4,"Value":630},{"Length":47,"Height":4,"Demand":0,"DemandMax":4,"Value":188},{"Length":21,"Height":5,"Demand":0,"DemandMax":4,"Value":105},{"Length":2,"Height":20,"Demand":0,"DemandMax":12,"Value":80},{"Length":23,"Height":24,"Demand":0,"DemandMax":4,"Value":552},{"Length":17,"Height":30,"Demand":0,"DemandMax":4,"Value":1020},{"Length":50,"Height":38,"Demand":0,"DemandMax":4,"Value":1900},{"Length":3,"Height":38,"Demand":0,"DemandMax":4,"Value":114},{"Length":10,"Height":94,"Demand":0,"DemandMax":4,"Value":2820},{"Length":49,"Height":97,"Demand":0,"DemandMax":4,"Value":4753},{"Length":42,"Height":99,"Demand":0,"DemandMax":4,"Value":8316},{"Length":12,"Height":47,"Demand":0,"DemandMax":8,"Value":564},{"Length":18,"Height":34,"Demand":0,"DemandMax":4,"Value":1224},{"Length":8,"Height":10,"Demand":0,"DemandMax":4,"Value":240},{"Length":7,"Height":50,"Demand":0,"DemandMax":4,"Value":350},{"Length":30,"Height":22,"Demand":0,"DemandMax":4,"Value":660},{"Length":10,"Height":40,"Demand":0,"DemandMax":4,"Value":800},{"Length":18,"Height":28,"Demand":0,"DemandMax":4,"Value":504},{"Length":34,"Height":49,"Demand":0,"DemandMax":4,"Value":1666},{"Length":7,"Height":93,"Demand":0,"DemandMax":4,"Value":1953},{"Length":17,"Height":41,"Demand":0,"DemandMax":4,"Value":697},{"Length":17,"Height":30,"Demand":0,"DemandMax":4,"Value":510},{"Length":26,"Height":29,"Demand":0,"DemandMax":4,"Value":1508},{"Length":18,"Height":49,"Demand":0,"DemandMax":4,"Value":882},{"Length":81,"Height":52,"Demand":0,"DemandMax":4,"Value":8424},{"Length":30,"Height":7,"Demand":0,"DemandMax":4,"Value":420},{"Length":45,"Height":18,"Demand":0,"DemandMax":4,"Value":2430},{"Length":37,"Height":94,"Demand":0,"DemandMax":4,"Value":10434},{"Length":45,"Height":13,"Demand":0,"DemandMax":4,"Value":585},{"Length":77,"Height":19,"Demand":0,"DemandMax":4,"Value":2926},{"Length":32,"Height":29,"Demand":0,"DemandMax":4,"Value":928},{"Length":45,"Height":10,"Demand":0,"DemandMax":4,"Value":1350},{"Length":47,"Height":7,"Demand":0,"DemandMax":8,"Value":329},{"Length":37,"Height":37,"Demand":0,"DemandMax":4,"Value":1369},{"Length":18,"Height":27,"Demand":0,"DemandMax":4,"Value":972},{"Length":26,"Height":15,"Demand":0,"DemandMax":4,"Value":390},{"Length":79,"Height":41,"Demand":0,"DemandMax":4,"Value":6478},{"Length":23,"Height":78,"Demand":0,"DemandMax":4,"Value":3588},{"Length":77,"Height":13,"Demand":0,"DemandMax":4,"Value":1001},{"Length":11,"Height":32,"Demand":0,"DemandMax":4,"Value":352},{"Length":21,"Height":50,"Demand":0,"DemandMax":4,"Value":3150},{"Length":13,"Height":11,"Demand":0,"DemandMax":4,"Value":143},{"Length":47,"Height":31,"Demand":0,"DemandMax":12,"Value":1457},{"Length":20,"Height":84,"Demand":0,"DemandMax":4,"Value":5040},{"Length":35,"Height":48,"Demand":0,"DemandMax":4,"Value":1680},{"Length":56,"Height":92,"Demand":0,"DemandMax":4,"Value":5152},{"Length":93,"Height":11,"Demand":0,"DemandMax":4,"Value":1023},{"Length":83,"Height":60,"Demand":0,"DemandMax":4,"Value":4980},{"Length":89,"Height":5,"Demand":0,"DemandMax":4,"Value":445},{"Length":92,"Height":9,"Demand":0,"DemandMax":4,"Value":2484},{"Length":31,"Height":91,"Demand":0,"DemandMax":4,"Value":5642},{"Length":12,"Height":88,"Demand":0,"DemandMax":4,"Value":2112},{"Length":25,"Height":29,"Demand":0,"DemandMax":4,"Value":1450},{"Length":6,"Height":49,"Demand":0,"DemandMax":4,"Value":882},{"Length":31,"Height":9,"Demand":0,"DemandMax":4,"Value":558},{"Length":36,"Height":86,"Demand":0,"DemandMax":4,"Value":3096},{"Length":42,"Height":13,"Demand":0,"DemandMax":4,"Value":546},{"Length":13,"Height":50,"Demand":0,"DemandMax":4,"Value":650},{"Length":42,"Height":39,"Demand":0,"DemandMax":4,"Value":3276},{"Length":19,"Height":12,"Demand":0,"DemandMax":4,"Value":228},{"Length":47,"Height":47,"Demand":0,"DemandMax":4,"Value":4418},{"Length":97,"Height":48,"Demand":0,"DemandMax":4,"Value":4656},{"Length":38,"Height":40,"Demand":0,"DemandMax":4,"Value":3040},{"Length":47,"Height":15,"Demand":0,"DemandMax":4,"Value":1410},{"Length":29,"Height":43,"Demand":0,"DemandMax":4,"Value":3741},{"Length":41,"Height":26,"Demand":0,"DemandMax":4,"Value":2132},{"Length":13,"Height":45,"Demand":0,"DemandMax":8,"Value":1755},{"Length":9,"Height":41,"Demand":0,"DemandMax":4,"Value":369},{"Length":31,"Height":25,"Demand":0,"DemandMax":4,"Value":775},{"Length":32,"Height":47,"Demand":0,"DemandMax":4,"Value":1504},{"Length":34,"Height":39,"Demand":0,"DemandMax":4,"Value":3978},{"Length":100,"Height":47,"Demand":0,"DemandMax":4,"Value":9400},{"Length":19,"Height":18,"Demand":0,"DemandMax":4,"Value":342},{"Length":22,"Height":19,"Demand":0,"DemandMax":8,"Value":836},{"Length":47,"Height":49,"Demand":0,"DemandMax":4,"Value":2303},{"Length":34,"Height":91,"Demand":0,"DemandMax":4,"Value":3094},{"Length":45,"Height":41,"Demand":0,"DemandMax":4,"Value":1845},{"Length":2,"Height":21,"Demand":0,"DemandMax":4,"Value":126},{"Length":11,"Height":78,"Demand":0,"DemandMax":4,"Value":2574},{"Length":28,"Height":35,"Demand":0,"DemandMax":4,"Value":2940},{"Length":8,"Height":41,"Demand":0,"DemandMax":4,"Value":328},{"Length":84,"Height":18,"Demand":0,"DemandMax":4,"Value":4536},{"Length":23,"Height":26,"Demand":0,"DemandMax":4,"Value":1794},{"Length":81,"Height":96,"Demand":0,"DemandMax":4,"Value":23328},{"Length":22,"Height":37,"Demand":0,"DemandMax":4,"Value":1628},{"Length":3,"Height":7,"Demand":0,"DemandMax":4,"Value":63},{"Length":93,"Height":15,"Demand":0,"DemandMax":4,"Value":4185},{"Length":25,"Height":3,"Demand":0,"DemandMax":4,"Value":225},{"Length":6,"Height":24,"Demand":0,"DemandMax":4,"Value":288},{"Length":7,"Height":4,"Demand":0,"DemandMax":4,"Value":56},{"Length":56,"Height":94,"Demand":0,"DemandMax":4,"Value":15792},{"Length":2,"Height":5,"Demand":0,"DemandMax":4,"Value":10},{"Length":23,"Height":34,"Demand":0,"DemandMax":4,"Value":1564},{"Length":86,"Height":70,"Demand":0,"DemandMax":4,"Value":6020},{"Length":15,"Height":79,"Demand":0,"DemandMax":8,"Value":1185},{"Length":39,"Height":27,"Demand":0,"DemandMax":4,"Value":3159},{"Length":26,"Height":98,"Demand":0,"DemandMax":4,"Value":2548},{"Length":8,"Height":8,"Demand":0,"DemandMax":4,"Value":192},{"Length":35,"Height":39,"Demand":0,"DemandMax":4,"Value":2730},{"Length":27,"Height":88,"Demand":0,"DemandMax":4,"Value":4752},{"Length":44,"Height":46,"Demand":0,"DemandMax":4,"Value":2024},{"Length":27,"Height":45,"Demand":0,"DemandMax":4,"Value":3645},{"Length":10,"Height":42,"Demand":0,"DemandMax":4,"Value":1260},{"Length":61,"Height":70,"Demand":0,"DemandMax":4,"Value":4270},{"Length":40,"Height":45,"Demand":0,"DemandMax":4,"Value":3600},{"Length":17,"Height":32,"Demand":0,"DemandMax":4,"Value":1088},{"Length":17,"Height":19,"Demand":0,"DemandMax":4,"Value":646},{"Length":24,"Height":39,"Demand":0,"DemandMax":4,"Value":2808},{"Length":39,"Height":13,"Demand":0,"DemandMax":4,"Value":507},{"Length":5,"Height":79,"Demand":0,"DemandMax":4,"Value":395},{"Length":50,"Height":25,"Demand":0,"DemandMax":4,"Value":3750},{"Length":60,"Height":83,"Demand":0,"DemandMax":4,"Value":4980},{"Length":45,"Height":50,"Demand":0,"DemandMax":4,"Value":6750},{"Length":29,"Height":11,"Demand":0,"DemandMax":4,"Value":957},{"Length":45,"Height":31,"Demand":0,"DemandMax":4,"Value":4185},{"Length":8,"Height":44,"Demand":0,"DemandMax":4,"Value":352},{"Length":25,"Height":23,"Demand":0,"DemandMax":4,"Value":1150},{"Length":38,"Height":77,"Demand":0,"DemandMax":4,"Value":8778},{"Length":93,"Height":47,"Demand":0,"DemandMax":4,"Value":8742},{"Length":4,"Height":3,"Demand":0,"DemandMax":4,"Value":36},{"Length":80,"Height":80,"Demand":0,"DemandMax":4,"Value":6400},{"Length":88,"Height":14,"Demand":0,"DemandMax":4,"Value":1232},{"Length":76,"Height":42,"Demand":0,"DemandMax":4,"Value":6384},{"Length":100,"Height":96,"Demand":0,"DemandMax":4,"Value":9600},{"Length":32,"Height":42,"Demand":0,"DemandMax":4,"Value":1344},{"Length":32,"Height":49,"Demand":0,"DemandMax":4,"Value":3136},{"Length":30,"Height":50,"Demand":0,"DemandMax":4,"Value":1500},{"Length":27,"Height":42,"Demand":0,"DemandMax":4,"Value":1134},{"Length":46,"Height":46,"Demand":0,"DemandMax":4,"Value":6348},{"Length":27,"Height":4,"Demand":0,"DemandMax":4,"Value":324},{"Length":99,"Height":16,"Demand":0,"DemandMax":4,"Value":3168},{"Length":37,"Height":14,"Demand":0,"DemandMax":4,"Value":1036},{"Length":46,"Height":13,"Demand":0,"DemandMax":4,"Value":1794},{"Length":46,"Height":19,"Demand":0,"DemandMax":4,"Value":1748},{"Length":31,"Height":48,"Demand":0,"DemandMax":4,"Value":4464},{"Length":77,"Height":32,"Demand":0,"DemandMax":4,"Value":7392},{"Length":40,"Height":35,"Demand":0,"DemandMax":8,"Value":4200},{"Length":38,"Height":6,"Demand":0,"DemandMax":4,"Value":228},{"Length":59,"Height":97,"Demand":0,"DemandMax":4,"Value":11446},{"Length":17,"Height":27,"Demand":0,"DemandMax":8,"Value":459},{"Length":87,"Height":57,"Demand":0,"DemandMax":4,"Value":4959},{"Length":29,"Height":9,"Demand":0,"DemandMax":4,"Value":783},{"Length":48,"Height":94,"Demand":0,"DemandMax":4,"Value":4512},{"Length":11,"Height":5,"Demand":0,"DemandMax":4,"Value":165},{"Length":79,"Height":26,"Demand":0,"DemandMax":4,"Value":4108},{"Length":91,"Height":43,"Demand":0,"DemandMax":4,"Value":3913},{"Length":38,"Height":7,"Demand":0,"DemandMax":4,"Value":532},{"Length":90,"Height":25,"Demand":0,"DemandMax":4,"Value":2250},{"Length":29,"Height":100,"Demand":0,"DemandMax":4,"Value":5800},{"Length":34,"Height":9,"Demand":0,"DemandMax":4,"Value":918},{"Length":31,"Height":31,"Demand":0,"DemandMax":4,"Value":2883},{"Length":44,"Height":39,"Demand":0,"DemandMax":4,"Value":3432},{"Length":96,"Height":13,"Demand":0,"DemandMax":4,"Value":1248},{"Length":4,"Height":31,"Demand":0,"DemandMax":4,"Value":124},{"Length":39,"Height":18,"Demand":0,"DemandMax":4,"Value":2106},{"Length":10,"Height":19,"Demand":0,"DemandMax":4,"Value":190},{"Length":11,"Height":5,"Demand":0,"DemandMax":4,"Value":55},{"Length":87,"Height":27,"Demand":0,"DemandMax":4,"Value":7047},{"Length":45,"Height":31,"Demand":0,"DemandMax":4,"Value":2790},{"Length":35,"Height":98,"Demand":0,"DemandMax":4,"Value":10290},{"Length":80,"Height":35,"Demand":0,"DemandMax":4,"Value":5600},{"Length":92,"Height":16,"Demand":0,"DemandMax":4,"Value":1472},{"Length":30,"Height":19,"Demand":0,"DemandMax":4,"Value":1710},{"Length":20,"Height":27,"Demand":0,"DemandMax":4,"Value":1620},{"Length":20,"Height":25,"Demand":0,"DemandMax":4,"Value":1000},{"Length":76,"Height":6,"Demand":0,"DemandMax":4,"Value":1368},{"Length":95,"Height":35,"Demand":0,"DemandMax":4,"Value":6650},{"Length":52,"Height":89,"Demand":0,"DemandMax":4,"Value":4628},{"Length":6,"Height":11,"Demand":0,"DemandMax":4,"Value":198},{"Length":48,"Height":16,"Demand":0,"DemandMax":4,"Value":1536},{"Length":47,"Height":32,"Demand":0,"DemandMax":4,"Value":1504},{"Length":4,"Height":83,"Demand":0,"DemandMax":4,"Value":996},{"Length":16,"Height":11,"Demand":0,"DemandMax":4,"Value":352},{"Length":8,"Height":6,"Demand":0,"DemandMax":4,"Value":144},{"Length":39,"Height":99,"Demand":0,"DemandMax":4,"Value":3861},{"Length":42,"Height":98,"Demand":0,"DemandMax":4,"Value":4116},{"Length":37,"Height":50,"Demand":0,"DemandMax":4,"Value":1850},{"Length":56,"Height":72,"Demand":0,"DemandMax":4,"Value":4032},{"Length":30,"Height":41,"Demand":0,"DemandMax":4,"Value":1230},{"Length":22,"Height":40,"Demand":0,"DemandMax":4,"Value":880},{"Length":16,"Height":30,"Demand":0,"DemandMax":4,"Value":960},{"Length":12,"Height":2,"Demand":0,"DemandMax":4,"Value":48},{"Length":40,"Height":25,"Demand":0,"DemandMax":4,"Value":1000},{"Length":16,"Height":23,"Demand":0,"DemandMax":4,"Value":368},{"Length":8,"Height":42,"Demand":0,"DemandMax":4,"Value":336},{"Length":75,"Height":74,"Demand":0,"DemandMax":4,"Value":16650},{"Length":2,"Height":44,"Demand":0,"DemandMax":4,"Value":176},{"Length":53,"Height":78,"Demand":0,"DemandMax":4,"Value":8268},{"Length":86,"Height":77,"Demand":0,"DemandMax":4,"Value":13244},{"Length":66,"Height":65,"Demand":0,"DemandMax":4,"Value":8580},{"Length":46,"Height":13,"Demand":0,"DemandMax":4,"Value":1196},{"Length":3,"Height":20,"Demand":0,"DemandMax":4,"Value":120},{"Length":14,"Height":7,"Demand":0,"DemandMax":4,"Value":294},{"Length":45,"Height":15,"Demand":0,"DemandMax":4,"Value":675},{"Length":38,"Height":44,"Demand":0,"DemandMax":4,"Value":3344},{"Length":50,"Height":40,"Demand":0,"DemandMax":4,"Value":2000},{"Length":84,"Height":57,"Demand":0,"DemandMax":4,"Value":14364},{"Length":6,"Height":95,"Demand":0,"DemandMax":4,"Value":1710},{"Length":36,"Height":45,"Demand":0,"DemandMax":4,"Value":4860},{"Length":43,"Height":13,"Demand":0,"DemandMax":4,"Value":1118},{"Length":14,"Height":30,"Demand":0,"DemandMax":4,"Value":1260},{"Length":44,"Height":24,"Demand":0,"DemandMax":4,"Value":2112},{"Length":30,"Height":33,"Demand":0,"DemandMax":4,"Value":990},{"Length":38,"Height":17,"Demand":0,"DemandMax":4,"Value":1938},{"Length":23,"Height":20,"Demand":0,"DemandMax":4,"Value":1380},{"Length":24,"Height":4,"Demand":0,"DemandMax":4,"Value":192},{"Length":31,"Height":46,"Demand":0,"DemandMax":4,"Value":1426},{"Length":15,"Height":46,"Demand":0,"DemandMax":4,"Value":1380},{"Length":14,"Height":28,"Demand":0,"DemandMax":4,"Value":784},{"Length":29,"Height":25,"Demand":0,"DemandMax":4,"Value":725},{"Length":20,"Height":6,"Demand":0,"DemandMax":4,"Value":360},{"Length":13,"Height":14,"Demand":0,"DemandMax":4,"Value":364},{"Length":28,"Height":2,"Demand":0,"DemandMax":4,"Value":112},{"Length":41,"Height":99,"Demand":0,"DemandMax":4,"Value":4059},{"Length":48,"Height":13,"Demand":0,"DemandMax":4,"Value":624},{"Length":34,"Height":30,"Demand":0,"DemandMax":4,"Value":3060},{"Length":46,"Height":22,"Demand":0,"DemandMax":4,"Value":3036},{"Length":2,"Height":82,"Demand":0,"DemandMax":4,"Value":328},{"Length":13,"Height":19,"Demand":0,"DemandMax":4,"Value":494},{"Length":19,"Height":16,"Demand":0,"DemandMax":4,"Value":608},{"Length":22,"Height":46,"Demand":0,"DemandMax":4,"Value":3036},{"Length":48,"Height":36,"Demand":0,"DemandMax":4,"Value":1728},{"Length":10,"Height":2,"Demand":0,"DemandMax":4,"Value":20},{"Length":23,"Height":38,"Demand":0,"DemandMax":4,"Value":2622},{"Length":36,"Height":79,"Demand":0,"DemandMax":4,"Value":5688},{"Length":49,"Height":43,"Demand":0,"DemandMax":8,"Value":4214},{"Length":11,"Height":16,"Demand":0,"DemandMax":8,"Value":528},{"Length":16,"Height":2,"Demand":0,"DemandMax":4,"Value":64},{"Length":43,"Height":26,"Demand":0,"DemandMax":4,"Value":1118},{"Length":28,"Height":20,"Demand":0,"DemandMax":4,"Value":1680},{"Length":9,"Height":33,"Demand":0,"DemandMax":4,"Value":594},{"Length":37,"Height":37,"Demand":0,"DemandMax":4,"Value":2738},{"Length":36,"Height":25,"Demand":0,"DemandMax":4,"Value":900},{"Length":82,"Height":60,"Demand":0,"DemandMax":4,"Value":4920},{"Length":34,"Height":50,"Demand":0,"DemandMax":4,"Value":1700},{"Length":3,"Height":89,"Demand":0,"DemandMax":4,"Value":534},{"Length":38,"Height":40,"Demand":0,"DemandMax":4,"Value":4560},{"Length":50,"Height":20,"Demand":0,"DemandMax":4,"Value":1000},{"Length":15,"Height":2,"Demand":0,"DemandMax":4,"Value":30},{"Length":6,"Height":19,"Demand":0,"DemandMax":4,"Value":228},{"Length":44,"Height":36,"Demand":0,"DemandMax":4,"Value":3168},{"Length":33,"Height":38,"Demand":0,"DemandMax":4,"Value":1254},{"Length":45,"Height":33,"Demand":0,"DemandMax":4,"Value":4455},{"Length":96,"Height":4,"Demand":0,"DemandMax":4,"Value":768},{"Length":84,"Height":27,"Demand":0,"DemandMax":4,"Value":4536},{"Length":18,"Height":93,"Demand":0,"DemandMax":4,"Value":3348},{"Length":35,"Height":9,"Demand":0,"DemandMax":4,"Value":945},{"Length":26,"Height":31,"Demand":0,"DemandMax":4,"Value":1612},{"Length":28,"Height":2,"Demand":0,"DemandMax":4,"Value":56},{"Length":44,"Height":14,"Demand":0,"DemandMax":4,"Value":1232},{"Length":21,"Height":43,"Demand":0,"DemandMax":4,"Value":903},{"Length":81,"Height":36,"Demand":0,"DemandMax":4,"Value":5832},{"Length":36,"Height":15,"Demand":0,"DemandMax":4,"Value":1080},{"Length":6,"Height":30,"Demand":0,"DemandMax":4,"Value":360},{"Length":36,"Height":37,"Demand":0,"DemandMax":4,"Value":3996},{"Length":82,"Height":26,"Demand":0,"DemandMax":4,"Value":6396},{"Length":79,"Height":14,"Demand":0,"DemandMax":4,"Value":2212},{"Length":49,"Height":29,"Demand":0,"DemandMax":4,"Value":2842},{"Length":3,"Height":41,"Demand":0,"DemandMax":4,"Value":369},{"Length":39,"Height":46,"Demand":0,"DemandMax":4,"Value":3588},{"Length":18,"Height":48,"Demand":0,"DemandMax":8,"Value":2592},{"Length":75,"Height":57,"Demand":0,"DemandMax":4,"Value":12825},{"Length":82,"Height":10,"Demand":0,"DemandMax":4,"Value":2460},{"Length":26,"Height":84,"Demand":0,"DemandMax":4,"Value":2184},{"Length":26,"Height":95,"Demand":0,"DemandMax":4,"Value":2470},{"Length":35,"Height":29,"Demand":0,"DemandMax":8,"Value":2030},{"Length":24,"Height":12,"Demand":0,"DemandMax":4,"Value":576},{"Length":83,"Height":42,"Demand":0,"DemandMax":4,"Value":6972},{"Length":30,"Height":17,"Demand":0,"DemandMax":4,"Value":1020},{"Length":20,"Height":44,"Demand":0,"DemandMax":4,"Value":2640},{"Length":92,"Height":43,"Demand":0,"DemandMax":4,"Value":11868},{"Length":43,"Height":32,"Demand":0,"DemandMax":4,"Value":2752},{"Length":28,"Height":7,"Demand":0,"DemandMax":8,"Value":392},{"Length":14,"Height":97,"Demand":0,"DemandMax":4,"Value":1358},{"Length":14,"Height":8,"Demand":0,"DemandMax":4,"Value":224},{"Length":72,"Height":52,"Demand":0,"DemandMax":4,"Value":11232},{"Length":40,"Height":6,"Demand":0,"DemandMax":4,"Value":480},{"Length":36,"Height":84,"Demand":0,"DemandMax":4,"Value":3024},{"Length":39,"Height":30,"Demand":0,"DemandMax":4,"Value":2340},{"Length":85,"Height":22,"Demand":0,"DemandMax":4,"Value":1870},{"Length":46,"Height":23,"Demand":0,"DemandMax":4,"Value":3174},{"Length":18,"Height":6,"Demand":0,"DemandMax":4,"Value":108},{"Length":9,"Height":26,"Demand":0,"DemandMax":4,"Value":702},{"Length":58,"Height":59,"Demand":0,"DemandMax":4,"Value":6844},{"Length":3,"Height":35,"Demand":0,"DemandMax":4,"Value":315},{"Length":66,"Height":64,"Demand":0,"DemandMax":4,"Value":8448},{"Length":44,"Height":20,"Demand":0,"DemandMax":8,"Value":880},{"Length":74,"Height":65,"Demand":0,"DemandMax":4,"Value":9620},{"Length":23,"Height":84,"Demand":0,"DemandMax":4,"Value":1932},{"Length":43,"Height":98,"Demand":0,"DemandMax":4,"Value":8428},{"Length":49,"Height":13,"Demand":0,"DemandMax":4,"Value":1274},{"Length":47,"Height":49,"Demand":0,"DemandMax":4,"Value":6909},{"Length":93,"Height":20,"Demand":0,"DemandMax":4,"Value":1860},{"Length":8,"Height":34,"Demand":0,"DemandMax":8,"Value":272},{"Length":4,"Height":49,"Demand":0,"DemandMax":4,"Value":196},{"Length":20,"Height":39,"Demand":0,"DemandMax":8,"Value":1560},{"Length":18,"Height":8,"Demand":0,"DemandMax":4,"Value":144},{"Length":21,"Height":44,"Demand":0,"DemandMax":4,"Value":2772},{"Length":44,"Height":83,"Demand":0,"DemandMax":4,"Value":10956},{"Length":42,"Height":3,"Demand":0,"DemandMax":4,"Value":252},{"Length":34,"Height":35,"Demand":0,"DemandMax":4,"Value":2380},{"Length":79,"Height":21,"Demand":0,"DemandMax":4,"Value":3318},{"Length":11,"Height":40,"Demand":0,"DemandMax":4,"Value":880},{"Length":37,"Height":34,"Demand":0,"DemandMax":4,"Value":3774},{"Length":83,"Height":45,"Demand":0,"DemandMax":4,"Value":3735},{"Length":18,"Height":23,"Demand":0,"DemandMax":4,"Value":1242},{"Length":4,"Height":38,"Demand":0,"DemandMax":4,"Value":456},{"Length":48,"Height":6,"Demand":0,"DemandMax":4,"Value":576},{"Length":79,"Height":10,"Demand":0,"DemandMax":4,"Value":1580},{"Length":27,"Height":32,"Demand":0,"DemandMax":4,"Value":2592},{"Length":29,"Height":42,"Demand":0,"DemandMax":8,"Value":2436},{"Length":20,"Height":15,"Demand":0,"DemandMax":4,"Value":300},{"Length":6,"Height":33,"Demand":0,"DemandMax":4,"Value":198},{"Length":97,"Height":4,"Demand":0,"DemandMax":4,"Value":388},{"Length":71,"Height":79,"Demand":0,"DemandMax":4,"Value":5609},{"Length":40,"Height":2,"Demand":0,"DemandMax":4,"Value":240},{"Length":17,"Height":41,"Demand":0,"DemandMax":4,"Value":2091},{"Length":5,"Height":77,"Demand":0,"DemandMax":4,"Value":385},{"Length":46,"Height":76,"Demand":0,"DemandMax":4,"Value":6992},{"Length":9,"Height":16,"Demand":0,"DemandMax":4,"Value":288},{"Length":37,"Height":48,"Demand":0,"DemandMax":4,"Value":1776},{"Length":11,"Height":45,"Demand":0,"DemandMax":4,"Value":990},{"Length":8,"Height":48,"Demand":0,"DemandMax":4,"Value":1152},{"Length":16,"Height":45,"Demand":0,"DemandMax":4,"Value":720},{"Length":82,"Height":31,"Demand":0,"DemandMax":4,"Value":5084},{"Length":35,"Height":85,"Demand":0,"DemandMax":4,"Value":2975},{"Length":40,"Height":23,"Demand":0,"DemandMax":4,"Value":2760},{"Length":89,"Height":80,"Demand":0,"DemandMax":4,"Value":7120},{"Length":23,"Height":8,"Demand":0,"DemandMax":4,"Value":184},{"Length":62,"Height":57,"Demand":0,"DemandMax":4,"Value":7068},{"Length":59,"Height":94,"Demand":0,"DemandMax":4,"Value":16638},{"Length":50,"Height":23,"Demand":0,"DemandMax":4,"Value":3450},{"Length":17,"Height":39,"Demand":0,"DemandMax":4,"Value":1326},{"Length":91,"Height":37,"Demand":0,"DemandMax":4,"Value":3367},{"Length":28,"Height":45,"Demand":0,"DemandMax":4,"Value":3780},{"Length":27,"Height":46,"Demand":0,"DemandMax":4,"Value":2484},{"Length":48,"Height":46,"Demand":0,"DemandMax":4,"Value":4416},{"Length":9,"Height":38,"Demand":0,"DemandMax":4,"Value":1026},{"Length":92,"Height":40,"Demand":0,"DemandMax":4,"Value":11040},{"Length":33,"Height":14,"Demand":0,"DemandMax":8,"Value":462},{"Length":77,"Height":39,"Demand":0,"DemandMax":4,"Value":3003},{"Length":2,"Height":13,"Demand":0,"DemandMax":4,"Value":26},{"Length":66,"Height":93,"Demand":0,"DemandMax":4,"Value":18414},{"Length":23,"Height":44,"Demand":0,"DemandMax":4,"Value":1012},{"Length":50,"Height":24,"Demand":0,"DemandMax":4,"Value":3600},{"Length":46,"Height":40,"Demand":0,"DemandMax":4,"Value":5520},{"Length":13,"Height":93,"Demand":0,"DemandMax":4,"Value":3627},{"Length":40,"Height":47,"Demand":0,"DemandMax":4,"Value":1880},{"Length":6,"Height":8,"Demand":0,"DemandMax":4,"Value":144},{"Length":8,"Height":96,"Demand":0,"DemandMax":4,"Value":1536},{"Length":14,"Height":22,"Demand":0,"DemandMax":4,"Value":308},{"Length":19,"Height":4,"Demand":0,"DemandMax":4,"Value":228},{"Length":50,"Height":22,"Demand":0,"DemandMax":4,"Value":1100},{"Length":82,"Height":90,"Demand":0,"DemandMax":4,"Value":7380},{"Length":7,"Height":44,"Demand":0,"DemandMax":4,"Value":616},{"Length":76,"Height":9,"Demand":0,"DemandMax":4,"Value":2052},{"Length":43,"Height":27,"Demand":0,"DemandMax":4,"Value":3483},{"Length":24,"Height":25,"Demand":0,"DemandMax":4,"Value":1200},{"Length":43,"Height":13,"Demand":0,"DemandMax":4,"Value":1677},{"Length":34,"Height":6,"Demand":0,"DemandMax":4,"Value":408},{"Length":25,"Height":38,"Demand":0,"DemandMax":4,"Value":2850},{"Length":76,"Height":35,"Demand":0,"DemandMax":4,"Value":5320},{"Length":26,"Height":92,"Demand":0,"DemandMax":4,"Value":4784},{"Length":35,"Height":39,"Demand":0,"DemandMax":4,"Value":1365},{"Length":9,"Height":20,"Demand":0,"DemandMax":4,"Value":540},{"Length":19,"Height":12,"Demand":0,"DemandMax":4,"Value":456},{"Length":30,"Height":30,"Demand":0,"DemandMax":4,"Value":2700},{"Length":39,"Height":33,"Demand":0,"DemandMax":4,"Value":1287},{"Length":71,"Height":67,"Demand":0,"DemandMax":4,"Value":14271},{"Length":89,"Height":91,"Demand":0,"DemandMax":4,"Value":8099},{"Length":22,"Height":33,"Demand":0,"DemandMax":4,"Value":726},{"Length":86,"Height":37,"Demand":0,"DemandMax":4,"Value":3182},{"Length":5,"Height":99,"Demand":0,"DemandMax":4,"Value":1485},{"Length":48,"Height":21,"Demand":0,"DemandMax":4,"Value":2016},{"Length":5,"Height":12,"Demand":0,"DemandMax":4,"Value":180},{"Length":66,"Height":56,"Demand":0,"DemandMax":4,"Value":7392},{"Length":3,"Height":13,"Demand":0,"DemandMax":4,"Value":78},{"Length":25,"Height":31,"Demand":0,"DemandMax":4,"Value":775},{"Length":5,"Height":28,"Demand":0,"DemandMax":4,"Value":280},{"Length":46,"Height":22,"Demand":0,"DemandMax":4,"Value":2024},{"Length":41,"Height":43,"Demand":0,"DemandMax":4,"Value":5289},{"Length":24,"Height":14,"Demand":0,"DemandMax":4,"Value":672},{"Length":58,"Height":95,"Demand":0,"DemandMax":4,"Value":5510},{"Length":31,"Height":83,"Demand":0,"DemandMax":4,"Value":2573},{"Length":33,"Height":31,"Demand":0,"DemandMax":4,"Value":2046},{"Length":45,"Height":42,"Demand":0,"DemandMax":4,"Value":1890},{"Length":61,"Height":66,"Demand":0,"DemandMax":4,"Value":4026},{"Length":42,"Height":2,"Demand":0,"DemandMax":4,"Value":84},{"Length":90,"Height":54,"Demand":0,"DemandMax":4,"Value":9720},{"Length":35,"Height":41,"Demand":0,"DemandMax":4,"Value":4305},{"Length":39,"Height":34,"Demand":0,"DemandMax":4,"Value":1326},{"Length":22,"Height":34,"Demand":0,"DemandMax":4,"Value":2244},{"Length":83,"Height":14,"Demand":0,"DemandMax":4,"Value":2324},{"Length":16,"Height":24,"Demand":0,"DemandMax":4,"Value":768},{"Length":21,"Height":25,"Demand":0,"DemandMax":4,"Value":1050},{"Length":47,"Height":33,"Demand":0,"DemandMax":4,"Value":3102},{"Length":19,"Height":34,"Demand":0,"DemandMax":4,"Value":646},{"Length":29,"Height":29,"Demand":0,"DemandMax":4,"Value":1682},{"Length":30,"Height":3,"Demand":0,"DemandMax":4,"Value":180},{"Length":3,"Height":11,"Demand":0,"DemandMax":4,"Value":99},{"Length":69,"Height":83,"Demand":0,"DemandMax":4,"Value":5727},{"Length":83,"Height":18,"Demand":0,"DemandMax":4,"Value":4482},{"Length":48,"Height":50,"Demand":0,"DemandMax":4,"Value":2400},{"Length":34,"Height":15,"Demand":0,"DemandMax":4,"Value":510},{"Length":9,"Height":18,"Demand":0,"DemandMax":4,"Value":324},{"Length":82,"Height":47,"Demand":0,"DemandMax":4,"Value":11562},{"Length":85,"Height":35,"Demand":0,"DemandMax":4,"Value":5950},{"Length":31,"Height":23,"Demand":0,"DemandMax":4,"Value":2139},{"Length":31,"Height":25,"Demand":0,"DemandMax":4,"Value":2325},{"Length":15,"Height":4,"Demand":0,"DemandMax":4,"Value":120},{"Length":11,"Height":46,"Demand":0,"DemandMax":4,"Value":1518},{"Length":33,"Height":15,"Demand":0,"DemandMax":4,"Value":495},{"Length":15,"Height":27,"Demand":0,"DemandMax":4,"Value":810},{"Length":46,"Height":43,"Demand":0,"DemandMax":4,"Value":5934},{"Length":45,"Height":50,"Demand":0,"DemandMax":4,"Value":4500},{"Length":50,"Height":91,"Demand":0,"DemandMax":4,"Value":9100},{"Length":55,"Height":70,"Demand":0,"DemandMax":4,"Value":7700},{"Length":63,"Height":65,"Demand":0,"DemandMax":4,"Value":4095},{"Length":34,"Height":12,"Demand":0,"DemandMax":4,"Value":816},{"Length":39,"Height":39,"Demand":0,"DemandMax":4,"Value":4563},{"Length":10,"Height":20,"Demand":0,"DemandMax":4,"Value":200},{"Length":83,"Height":57,"Demand":0,"DemandMax":4,"Value":9462},{"Length":14,"Height":43,"Demand":0,"DemandMax":4,"Value":1204},{"Length":27,"Height":45,"Demand":0,"DemandMax":4,"Value":2430},{"Length":3,"Height":16,"Demand":0,"DemandMax":4,"Value":48},{"Length":7,"Height":9,"Demand":0,"DemandMax":4,"Value":63},{"Length":16,"Height":80,"Demand":0,"DemandMax":4,"Value":1280},{"Length":33,"Height":41,"Demand":0,"DemandMax":4,"Value":1353},{"Length":37,"Height":32,"Demand":0,"DemandMax":4,"Value":3552},{"Length":37,"Height":12,"Demand":0,"DemandMax":4,"Value":1332},{"Length":24,"Height":20,"Demand":0,"DemandMax":4,"Value":960},{"Length":28,"Height":40,"Demand":0,"DemandMax":4,"Value":2240},{"Length":49,"Height":25,"Demand":0,"DemandMax":4,"Value":3675},{"Length":38,"Height":36,"Demand":0,"DemandMax":4,"Value":4104},{"Length":46,"Height":9,"Demand":0,"DemandMax":4,"Value":1242},{"Length":38,"Height":35,"Demand":0,"DemandMax":4,"Value":1330},{"Length":16,"Height":45,"Demand":0,"DemandMax":4,"Value":2160},{"Length":60,"Height":55,"Demand":0,"DemandMax":4,"Value":6600},{"Length":34,"Height":27,"Demand":0,"DemandMax":4,"Value":1836},{"Length":26,"Height":43,"Demand":0,"DemandMax":4,"Value":2236},{"Length":14,"Height":17,"Demand":0,"DemandMax":4,"Value":476},{"Length":2,"Height":29,"Demand":0,"DemandMax":4,"Value":116},{"Length":6,"Height":39,"Demand":0,"DemandMax":4,"Value":468},{"Length":32,"Height":10,"Demand":0,"DemandMax":4,"Value":960},{"Length":83,"Height":3,"Demand":0,"DemandMax":4,"Value":249},{"Length":27,"Height":24,"Demand":0,"DemandMax":4,"Value":648},{"Length":48,"Height":23,"Demand":0,"DemandMax":4,"Value":3312},{"Length":43,"Height":33,"Demand":0,"DemandMax":4,"Value":1419},{"Length":82,"Height":39,"Demand":0,"DemandMax":4,"Value":9594},{"Length":22,"Height":36,"Demand":0,"DemandMax":8,"Value":792},{"Length":20,"Height":84,"Demand":0,"DemandMax":4,"Value":1680},{"Length":26,"Height":6,"Demand":0,"DemandMax":4,"Value":312},{"Length":23,"Height":35,"Demand":0,"DemandMax":8,"Value":805},{"Length":16,"Height":15,"Demand":0,"DemandMax":4,"Value":720},{"Length":28,"Height":46,"Demand":0,"DemandMax":4,"Value":2576},{"Length":51,"Height":79,"Demand":0,"DemandMax":4,"Value":12087},{"Length":95,"Height":23,"Demand":0,"DemandMax":4,"Value":4370},{"Length":34,"Height":33,"Demand":0,"DemandMax":4,"Value":1122},{"Length":98,"Height":5,"Demand":0,"DemandMax":4,"Value":490},{"Length":3,"Height":86,"Demand":0,"DemandMax":4,"Value":516},{"Length":17,"Height":10,"Demand":0,"DemandMax":4,"Value":510},{"Length":29,"Height":12,"Demand":0,"DemandMax":4,"Value":1044},{"Length":28,"Height":25,"Demand":0,"DemandMax":4,"Value":700},{"Length":27,"Height":29,"Demand":0,"DemandMax":4,"Value":783},{"Length":26,"Height":36,"Demand":0,"DemandMax":4,"Value":936},{"Length":17,"Height":4,"Demand":0,"DemandMax":4,"Value":136},{"Length":51,"Height":66,"Demand":0,"DemandMax":4,"Value":6732},{"Length":19,"Height":6,"Demand":0,"DemandMax":4,"Value":342},{"Length":16,"Height":13,"Demand":0,"DemandMax":8,"Value":208},{"Length":3,"Height":36,"Demand":0,"DemandMax":4,"Value":324},{"Length":83,"Height":12,"Demand":0,"DemandMax":4,"Value":996},{"Length":32,"Height":32,"Demand":0,"DemandMax":8,"Value":3072},{"Length":33,"Height":19,"Demand":0,"DemandMax":4,"Value":1254},{"Length":3,"Height":23,"Demand":0,"DemandMax":4,"Value":207},{"Length":49,"Height":5,"Demand":0,"DemandMax":4,"Value":735},{"Length":23,"Height":15,"Demand":0,"DemandMax":4,"Value":345},{"Length":48,"Height":26,"Demand":0,"DemandMax":4,"Value":1248},{"Length":2,"Height":21,"Demand":0,"DemandMax":4,"Value":42},{"Length":18,"Height":30,"Demand":0,"DemandMax":4,"Value":1080},{"Length":33,"Height":13,"Demand":0,"DemandMax":4,"Value":429},{"Length":9,"Height":47,"Demand":0,"DemandMax":4,"Value":423},{"Length":7,"Height":36,"Demand":0,"DemandMax":4,"Value":252},{"Length":20,"Height":9,"Demand":0,"DemandMax":4,"Value":180},{"Length":85,"Height":17,"Demand":0,"DemandMax":4,"Value":2890},{"Length":41,"Height":3,"Demand":0,"DemandMax":4,"Value":369},{"Length":22,"Height":3,"Demand":0,"DemandMax":4,"Value":132},{"Length":15,"Height":43,"Demand":0,"DemandMax":4,"Value":1290},{"Length":29,"Height":32,"Demand":0,"DemandMax":4,"Value":928},{"Length":13,"Height":28,"Demand":0,"DemandMax":4,"Value":1092},{"Length":42,"Height":25,"Demand":0,"DemandMax":4,"Value":1050},{"Length":13,"Height":95,"Demand":0,"DemandMax":4,"Value":2470},{"Length":16,"Height":32,"Demand":0,"DemandMax":4,"Value":1536},{"Length":17,"Height":23,"Demand":0,"DemandMax":4,"Value":391},{"Length":14,"Height":49,"Demand":0,"DemandMax":4,"Value":686},{"Length":30,"Height":25,"Demand":0,"DemandMax":4,"Value":1500},{"Length":97,"Height":38,"Demand":0,"DemandMax":4,"Value":3686},{"Length":50,"Height":11,"Demand":0,"DemandMax":4,"Value":1100},{"Length":6,"Height":31,"Demand":0,"DemandMax":4,"Value":186},{"Length":43,"Height":84,"Demand":0,"DemandMax":4,"Value":7224},{"Length":31,"Height":23,"Demand":0,"DemandMax":4,"Value":713},{"Length":22,"Height":32,"Demand":0,"DemandMax":4,"Value":1408},{"Length":42,"Height":83,"Demand":0,"DemandMax":4,"Value":6972},{"Length":18,"Height":24,"Demand":0,"DemandMax":4,"Value":432},{"Length":93,"Height":35,"Demand":0,"DemandMax":4,"Value":9765},{"Length":4,"Height":9,"Demand":0,"DemandMax":4,"Value":36},{"Length":46,"Height":27,"Demand":0,"DemandMax":4,"Value":2484},{"Length":15,"Height":25,"Demand":0,"DemandMax":4,"Value":750},{"Length":5,"Height":86,"Demand":0,"DemandMax":4,"Value":430},{"Length":50,"Height":6,"Demand":0,"DemandMax":4,"Value":600},{"Length":20,"Height":5,"Demand":0,"DemandMax":4,"Value":300},{"Length":46,"Height":49,"Demand":0,"DemandMax":4,"Value":4508},{"Length":11,"Height":42,"Demand":0,"DemandMax":4,"Value":924},{"Length":19,"Height":87,"Demand":0,"DemandMax":4,"Value":3306},{"Length":25,"Height":26,"Demand":0,"DemandMax":4,"Value":650},{"Length":17,"Height":6,"Demand":0,"DemandMax":4,"Value":102},{"Length":28,"Height":96,"Demand":0,"DemandMax":4,"Value":8064},{"Length":57,"Height":71,"Demand":0,"DemandMax":4,"Value":12141},{"Length":76,"Height":98,"Demand":0,"DemandMax":4,"Value":22344},{"Length":15,"Height":45,"Demand":0,"DemandMax":4,"Value":2025},{"Length":71,"Height":60,"Demand":0,"DemandMax":4,"Value":12780},{"Length":81,"Height":44,"Demand":0,"DemandMax":4,"Value":10692},{"Length":17,"Height":34,"Demand":0,"DemandMax":4,"Value":1156},{"Length":54,"Height":75,"Demand":0,"DemandMax":4,"Value":4050},{"Length":10,"Height":83,"Demand":0,"DemandMax":4,"Value":2490},{"Length":3,"Height":93,"Demand":0,"DemandMax":4,"Value":279},{"Length":26,"Height":42,"Demand":0,"DemandMax":4,"Value":2184},{"Length":89,"Height":8,"Demand":0,"DemandMax":4,"Value":712},{"Length":26,"Height":12,"Demand":0,"DemandMax":4,"Value":312},{"Length":34,"Height":22,"Demand":0,"DemandMax":4,"Value":748},{"Length":7,"Height":100,"Demand":0,"DemandMax":4,"Value":2100},{"Length":15,"Height":12,"Demand":0,"DemandMax":4,"Value":180},{"Length":37,"Height":8,"Demand":0,"DemandMax":4,"Value":888},{"Length":54,"Height":69,"Demand":0,"DemandMax":4,"Value":3726},{"Length":44,"Height":83,"Demand":0,"DemandMax":4,"Value":7304},{"Length":11,"Height":31,"Demand":0,"DemandMax":4,"Value":682},{"Length":15,"Height":26,"Demand":0,"DemandMax":4,"Value":1170},{"Length":12,"Height":90,"Demand":0,"DemandMax":4,"Value":3240},{"Length":44,"Height":81,"Demand":0,"DemandMax":4,"Value":10692},{"Length":30,"Height":6,"Demand":0,"DemandMax":4,"Value":360},{"Length":60,"Height":61,"Demand":0,"DemandMax":4,"Value":3660},{"Length":14,"Height":26,"Demand":0,"DemandMax":4,"Value":1092},{"Length":50,"Height":37,"Demand":0,"DemandMax":4,"Value":3700},{"Length":88,"Height":86,"Demand":0,"DemandMax":4,"Value":15136},{"Length":88,"Height":46,"Demand":0,"DemandMax":4,"Value":8096},{"Length":13,"Height":16,"Demand":0,"DemandMax":4,"Value":624},{"Length":27,"Height":21,"Demand":0,"DemandMax":4,"Value":567},{"Length":81,"Height":33,"Demand":0,"DemandMax":4,"Value":2673},{"Length":44,"Height":16,"Demand":0,"DemandMax":4,"Value":2112},{"Length":12,"Height":44,"Demand":0,"DemandMax":4,"Value":528},{"Length":98,"Height":61,"Demand":0,"DemandMax":4,"Value":5978},{"Length":29,"Height":83,"Demand":0,"DemandMax":4,"Value":2407},{"Length":37,"Height":15,"Demand":0,"DemandMax":4,"Value":555},{"Length":20,"Height":40,"Demand":0,"DemandMax":4,"Value":800},{"Length":7,"Height":50,"Demand":0,"DemandMax":4,"Value":1050},{"Length":29,"Height":13,"Demand":0,"DemandMax":4,"Value":754},{"Length":100,"Height":78,"Demand":0,"DemandMax":4,"Value":15600},{"Length":19,"Height":43,"Demand":0,"DemandMax":4,"Value":2451},{"Length":16,"Height":49,"Demand":0,"DemandMax":8,"Value":2352},{"Length":38,"Height":94,"Demand":0,"DemandMax":4,"Value":7144},{"Length":3,"Height":32,"Demand":0,"DemandMax":4,"Value":96},{"Length":32,"Height":42,"Demand":0,"DemandMax":4,"Value":4032},{"Length":98,"Height":96,"Demand":0,"DemandMax":4,"Value":28224},{"Length":73,"Height":55,"Demand":0,"DemandMax":4,"Value":4015},{"Length":17,"Height":8,"Demand":0,"DemandMax":4,"Value":408},{"Length":43,"Height":31,"Demand":0,"DemandMax":4,"Value":2666},{"Length":19,"Height":5,"Demand":0,"DemandMax":4,"Value":285},{"Length":35,"Height":21,"Demand":0,"DemandMax":4,"Value":2205},{"Length":50,"Height":29,"Demand":0,"DemandMax":4,"Value":2900},{"Length":41,"Height":50,"Demand":0,"DemandMax":4,"Value":6150},{"Length":82,"Height":28,"Demand":0,"DemandMax":4,"Value":6888},{"Length":93,"Height":65,"Demand":0,"DemandMax":4,"Value":6045},{"Length":38,"Height":43,"Demand":0,"DemandMax":4,"Value":1634},{"Length":6,"Height":4,"Demand":0,"DemandMax":4,"Value":72},{"Length":18,"Height":36,"Demand":0,"DemandMax":4,"Value":1944},{"Length":96,"Height":55,"Demand":0,"DemandMax":4,"Value":5280},{"Length":10,"Height":36,"Demand":0,"DemandMax":4,"Value":360},{"Length":34,"Height":14,"Demand":0,"DemandMax":4,"Value":1428},{"Length":12,"Height":3,"Demand":0,"DemandMax":4,"Value":72},{"Length":83,"Height":33,"Demand":0,"DemandMax":4,"Value":8217},{"Length":49,"Height":30,"Demand":0,"DemandMax":4,"Value":2940},{"Length":49,"Height":36,"Demand":0,"DemandMax":4,"Value":1764},{"Length":24,"Height":27,"Demand":0,"DemandMax":4,"Value":1944},{"Length":31,"Height":31,"Demand":0,"DemandMax":8,"Value":1922},{"Length":37,"Height":9,"Demand":0,"DemandMax":4,"Value":666},{"Length":3,"Height":35,"Demand":0,"DemandMax":4,"Value":105},{"Length":96,"Height":63,"Demand":0,"DemandMax":4,"Value":12096},{"Length":10,"Height":34,"Demand":0,"DemandMax":4,"Value":1020},{"Length":50,"Height":16,"Demand":0,"DemandMax":4,"Value":1600},{"Length":12,"Height":19,"Demand":0,"DemandMax":4,"Value":456},{"Length":84,"Height":50,"Demand":0,"DemandMax":4,"Value":8400},{"Length":8,"Height":38,"Demand":0,"DemandMax":4,"Value":608},{"Length":47,"Height":25,"Demand":0,"DemandMax":4,"Value":2350},{"Length":25,"Height":13,"Demand":0,"DemandMax":4,"Value":650},{"Length":93,"Height":54,"Demand":0,"DemandMax":4,"Value":5022},{"Length":33,"Height":3,"Demand":0,"DemandMax":4,"Value":198},{"Length":77,"Height":95,"Demand":0,"DemandMax":4,"Value":14630},{"Length":33,"Height":10,"Demand":0,"DemandMax":4,"Value":330},{"Length":15,"Height":32,"Demand":0,"DemandMax":4,"Value":1440},{"Length":9,"Height":40,"Demand":0,"DemandMax":4,"Value":1080},{"Length":10,"Height":20,"Demand":0,"DemandMax":4,"Value":400},{"Length":44,"Height":5,"Demand":0,"DemandMax":4,"Value":660},{"Length":4,"Height":41,"Demand":0,"DemandMax":4,"Value":164},{"Length":84,"Height":13,"Demand":0,"DemandMax":4,"Value":1092},{"Length":18,"Height":78,"Demand":0,"DemandMax":4,"Value":4212},{"Length":94,"Height":14,"Demand":0,"DemandMax":4,"Value":1316},{"Length":8,"Height":80,"Demand":0,"DemandMax":4,"Value":640},{"Length":94,"Height":18,"Demand":0,"DemandMax":4,"Value":1692},{"Length":27,"Height":28,"Demand":0,"DemandMax":4,"Value":756},{"Length":92,"Height":28,"Demand":0,"DemandMax":4,"Value":5152},{"Length":23,"Height":6,"Demand":0,"DemandMax":4,"Value":276},{"Length":43,"Height":11,"Demand":0,"DemandMax":4,"Value":946},{"Length":81,"Height":46,"Demand":0,"DemandMax":4,"Value":3726},{"Length":85,"Height":27,"Demand":0,"DemandMax":4,"Value":2295},{"Length":84,"Height":59,"Demand":0,"DemandMax":4,"Value":9912},{"Length":92,"Height":47,"Demand":0,"DemandMax":4,"Value":4324},{"Length":34,"Height":5,"Demand":0,"DemandMax":4,"Value":510},{"Length":37,"Height":45,"Demand":0,"DemandMax":4,"Value":1665},{"Length":41,"Height":27,"Demand":0,"DemandMax":4,"Value":3321},{"Length":14,"Height":34,"Demand":0,"DemandMax":4,"Value":476},{"Length":37,"Height":39,"Demand":0,"DemandMax":4,"Value":2886},{"Length":89,"Height":81,"Demand":0,"DemandMax":4,"Value":21627},{"Length":87,"Height":88,"Demand":0,"DemandMax":4,"Value":15312},{"Length":11,"Height":38,"Demand":0,"DemandMax":4,"Value":1254},{"Length":50,"Height":3,"Demand":0,"DemandMax":4,"Value":150},{"Length":8,"Height":30,"Demand":0,"DemandMax":4,"Value":720},{"Length":41,"Height":10,"Demand":0,"DemandMax":4,"Value":410},{"Length":40,"Height":17,"Demand":0,"DemandMax":4,"Value":1360},{"Length":7,"Height":15,"Demand":0,"DemandMax":4,"Value":105},{"Length":29,"Height":28,"Demand":0,"DemandMax":4,"Value":812},{"Length":96,"Height":7,"Demand":0,"DemandMax":4,"Value":2016},{"Length":21,"Height":11,"Demand":0,"DemandMax":4,"Value":693},{"Length":25,"Height":45,"Demand":0,"DemandMax":4,"Value":3375},{"Length":44,"Height":34,"Demand":0,"DemandMax":4,"Value":4488},{"Length":52,"Height":62,"Demand":0,"DemandMax":4,"Value":6448},{"Length":15,"Height":19,"Demand":0,"DemandMax":4,"Value":570},{"Length":7,"Height":3,"Demand":0,"DemandMax":4,"Value":42},{"Length":7,"Height":6,"Demand":0,"DemandMax":4,"Value":42},{"Length":77,"Height":55,"Demand":0,"DemandMax":4,"Value":4235},{"Length":19,"Height":24,"Demand":0,"DemandMax":4,"Value":1368},{"Length":68,"Height":90,"Demand":0,"DemandMax":4,"Value":12240},{"Length":38,"Height":26,"Demand":0,"DemandMax":4,"Value":1976},{"Length":100,"Height":94,"Demand":0,"DemandMax":4,"Value":28200},{"Length":7,"Height":6,"Demand":0,"DemandMax":4,"Value":84},{"Length":73,"Height":78,"Demand":0,"DemandMax":4,"Value":11388},{"Length":19,"Height":28,"Demand":0,"DemandMax":4,"Value":1064},{"Length":46,"Height":40,"Demand":0,"DemandMax":4,"Value":1840},{"Length":23,"Height":33,"Demand":0,"DemandMax":4,"Value":759},{"Length":39,"Height":9,"Demand":0,"DemandMax":4,"Value":351},{"Length":81,"Height":21,"Demand":0,"DemandMax":4,"Value":1701},{"Length":3,"Height":76,"Demand":0,"DemandMax":4,"Value":456},{"Length":28,"Height":19,"Demand":0,"DemandMax":4,"Value":532},{"Length":11,"Height":46,"Demand":0,"DemandMax":4,"Value":506},{"Length":76,"Height":47,"Demand":0,"DemandMax":4,"Value":10716},{"Length":34,"Height":48,"Demand":0,"DemandMax":4,"Value":3264},{"Length":26,"Height":95,"Demand":0,"DemandMax":4,"Value":4940},{"Length":44,"Height":16,"Demand":0,"DemandMax":4,"Value":704},{"Length":22,"Height":43,"Demand":0,"DemandMax":4,"Value":946},{"Length":97,"Height":30,"Demand":0,"DemandMax":4,"Value":8730},{"Length":46,"Height":91,"Demand":0,"DemandMax":4,"Value":8372},{"Length":79,"Height":88,"Demand":0,"DemandMax":4,"Value":6952},{"Length":10,"Height":45,"Demand":0,"DemandMax":4,"Value":1350},{"Length":65,"Height":83,"Demand":0,"DemandMax":4,"Value":5395},{"Length":19,"Height":23,"Demand":0,"DemandMax":4,"Value":874},{"Length":40,"Height":46,"Demand":0,"DemandMax":4,"Value":1840},{"Length":14,"Height":12,"Demand":0,"DemandMax":4,"Value":336},{"Length":52,"Height":65,"Demand":0,"DemandMax":4,"Value":6760},{"Length":93,"Height":49,"Demand":0,"DemandMax":4,"Value":4557},{"Length":24,"Height":37,"Demand":0,"DemandMax":4,"Value":1776},{"Length":34,"Height":10,"Demand":0,"DemandMax":4,"Value":1020},{"Length":29,"Height":48,"Demand":0,"DemandMax":4,"Value":1392},{"Length":11,"Height":19,"Demand":0,"DemandMax":4,"Value":627},{"Length":87,"Height":76,"Demand":0,"DemandMax":4,"Value":19836},{"Length":6,"Height":90,"Demand":0,"DemandMax":4,"Value":1080},{"Length":52,"Height":76,"Demand":0,"DemandMax":4,"Value":11856},{"Length":41,"Height":34,"Demand":0,"DemandMax":4,"Value":4182},{"Length":21,"Height":14,"Demand":0,"DemandMax":4,"Value":882},{"Length":36,"Height":43,"Demand":0,"DemandMax":4,"Value":4644},{"Length":33,"Height":3,"Demand":0,"DemandMax":4,"Value":99},{"Length":22,"Height":7,"Demand":0,"DemandMax":4,"Value":154},{"Length":35,"Height":5,"Demand":0,"DemandMax":4,"Value":350},{"Length":50,"Height":25,"Demand":0,"DemandMax":4,"Value":1250},{"Length":35,"Height":23,"Demand":0,"DemandMax":4,"Value":1610},{"Length":2,"Height":33,"Demand":0,"DemandMax":4,"Value":66},{"Length":46,"Height":25,"Demand":0,"DemandMax":4,"Value":2300},{"Length":39,"Height":19,"Demand":0,"DemandMax":4,"Value":741},{"Length":37,"Height":79,"Demand":0,"DemandMax":4,"Value":2923},{"Length":47,"Height":13,"Demand":0,"DemandMax":4,"Value":611},{"Length":90,"Height":30,"Demand":0,"DemandMax":4,"Value":8100},{"Length":84,"Height":77,"Demand":0,"DemandMax":4,"Value":19404},{"Length":82,"Height":23,"Demand":0,"DemandMax":4,"Value":3772},{"Length":35,"Height":34,"Demand":0,"DemandMax":4,"Value":1190},{"Length":66,"Height":95,"Demand":0,"DemandMax":4,"Value":6270},{"Length":29,"Height":30,"Demand":0,"DemandMax":4,"Value":2610},{"Length":39,"Height":7,"Demand":0,"DemandMax":8,"Value":273},{"Length":92,"Height":24,"Demand":0,"DemandMax":4,"Value":4416},{"Length":92,"Height":27,"Demand":0,"DemandMax":4,"Value":2484},{"Length":17,"Height":50,"Demand":0,"DemandMax":4,"Value":1700},{"Length":59,"Height":56,"Demand":0,"DemandMax":4,"Value":3304},{"Length":77,"Height":6,"Demand":0,"DemandMax":4,"Value":462},{"Length":24,"Height":5,"Demand":0,"DemandMax":4,"Value":360},{"Length":34,"Height":82,"Demand":0,"DemandMax":4,"Value":5576},{"Length":35,"Height":29,"Demand":0,"DemandMax":4,"Value":3045},{"Length":46,"Height":78,"Demand":0,"DemandMax":4,"Value":7176},{"Length":39,"Height":49,"Demand":0,"DemandMax":4,"Value":1911},{"Length":100,"Height":18,"Demand":0,"DemandMax":4,"Value":5400},{"Length":2,"Height":11,"Demand":0,"DemandMax":4,"Value":66},{"Length":5,"Height":11,"Demand":0,"DemandMax":4,"Value":110},{"Length":92,"Height":27,"Demand":0,"DemandMax":4,"Value":4968},{"Length":39,"Height":27,"Demand":0,"DemandMax":4,"Value":2106},{"Length":99,"Height":38,"Demand":0,"DemandMax":4,"Value":11286},{"Length":38,"Height":23,"Demand":0,"DemandMax":4,"Value":2622},{"Length":18,"Height":35,"Demand":0,"DemandMax":4,"Value":630},{"Length":48,"Height":14,"Demand":0,"DemandMax":4,"Value":2016},{"Length":23,"Height":50,"Demand":0,"DemandMax":4,"Value":1150},{"Length":5,"Height":39,"Demand":0,"DemandMax":4,"Value":585},{"Length":22,"Height":13,"Demand":0,"DemandMax":4,"Value":858},{"Length":76,"Height":34,"Demand":0,"DemandMax":4,"Value":5168},{"Length":29,"Height":2,"Demand":0,"DemandMax":4,"Value":58},{"Length":25,"Height":15,"Demand":0,"DemandMax":4,"Value":375},{"Length":68,"Height":89,"Demand":0,"DemandMax":4,"Value":6052},{"Length":22,"Height":33,"Demand":0,"DemandMax":4,"Value":2178},{"Length":45,"Height":27,"Demand":0,"DemandMax":4,"Value":3645},{"Length":3,"Height":18,"Demand":0,"DemandMax":4,"Value":108},{"Length":25,"Height":97,"Demand":0,"DemandMax":4,"Value":2425},{"Length":20,"Height":43,"Demand":0,"DemandMax":4,"Value":1720},{"Length":45,"Height":94,"Demand":0,"DemandMax":4,"Value":8460},{"Length":33,"Height":5,"Demand":0,"DemandMax":4,"Value":165},{"Length":65,"Height":97,"Demand":0,"DemandMax":4,"Value":6305},{"Length":23,"Height":5,"Demand":0,"DemandMax":4,"Value":115},{"Length":5,"Height":19,"Demand":0,"DemandMax":4,"Value":95},{"Length":14,"Height":24,"Demand":0,"DemandMax":4,"Value":1008},{"Length":17,"Height":12,"Demand":0,"DemandMax":4,"Value":408},{"Length":49,"Height":47,"Demand":0,"DemandMax":4,"Value":4606},{"Length":22,"Height":91,"Demand":0,"DemandMax":4,"Value":6006},{"Length":12,"Height":14,"Demand":0,"DemandMax":4,"Value":504},{"Length":67,"Height":67,"Demand":0,"DemandMax":4,"Value":8978}]}