{"Name":"C3_40_S_10","Objects":[{"Length":100,"Height":100,"Stock":null,"Cost":10000}],"Items":[{"Length":40,"Height":16,"Demand":1,"DemandMax":null,"Value":640},{"Length":23,"Height":40,"Demand":1,"DemandMax":null,"Value":920},{"Length":33,"Height":49,"Demand":1,"DemandMax":null,"Value":1617},{"Length":13,"Height":32,"Demand":1,"DemandMax":null,"Value":416},{"Length":27,"Height":22,"Demand":1,"DemandMax":null,"Value":594},{"Length":30,"Height":39,"Demand":1,"DemandMax":null,"Value":1170},{"Length":12,"Height":21,"Demand":1,"DemandMax":null,"Value":252},{"Length":15,"Height":17,"Demand":1,"DemandMax":null,"Value":255},{"Length":19,"Height":14,"Demand":1,"DemandMax":null,"Value":266},{"Length":37,"Height":37,"Demand":1,"DemandMax":null,"Value":1369},{"Length":41,"Height":46,"Demand":1,"DemandMax":null,"Value":1886},{"Length":16,"Height":42,"Demand":1,"DemandMax":null,"Value":672},{"Length":28,"Height":38,"Demand":1,"DemandMax":null,"Value":1064},{"Length":42,"Height":12,"Demand":1,"DemandMax":null,"Value":504},{"Length":45,"Height":43,"Demand":1,"DemandMax":null,"Value":1935},{"Length":20,"Height":19,"Demand":1,"DemandMax":null,"Value":380},{"Length":47,"Height":30,"Demand":1,"DemandMax":null,"Value":1410},{"Length":14,"Height":17,"Demand":1,"DemandMax":null,"Value":238},{"Length":18,"Height":20,"Demand":1,"DemandMax":null,"Value":360},{"Length":17,"Height":41,"Demand":1,"DemandMax":null,"Value":697},{"Length":41,"Height":32,"Demand":1,"DemandMax":null,"Value":1312},{"Length":15,"Height":20,"Demand":1,"DemandMax":null,"Value":300},{"Length":42,"Height":30,"Demand":1,"DemandMax":null,"Value":1260},{"Length":43,"Height":30,"Demand":1,"DemandMax":null,"Value":1290},{"Length":19,"Height":12,"Demand":1,"DemandMax":null,"Value":228},{"Length":15,"Height":13,"Demand":1,"DemandMax":null,"Value":195},{"Length":24,"Height":32,"Demand":1,"DemandMax":null,"Value":768},{"Length":43,"Height":43,"Demand":1,"DemandMax":null,"Value":1849},{"Length":13,"Height":42,"Demand":1,"DemandMax":null,"Value":546},{"Length":34,"Height":24,"Demand":1,"DemandMax":null,"Value":816},{"Length":20,"Height":49,"Demand":1,"DemandMax":null,"Value":980},{"Length":38,"Height":45,"Demand":1,"DemandMax":null,"Value":1710},{"Length":10,"Height":45,"Demand":1,"DemandMax":null,"Value":450},{"Length":25,"Height":23,"Demand":1,"DemandMax":null,"Value":575},{"Length":34,"Height":41,"Demand":1,"DemandMax":null,"Value":1394},{"Length":21,"Height":19,"Demand":1,"DemandMax":null,"Value":399},{"Length":37,"Height":20,"Demand":1,"DemandMax":null,"Value":740},{"Length":40,"Height":22,"Demand":1,"DemandMax":null,"Value":880},{"Length":14,"Height":22,"Demand":1,"DemandMax":null,"Value":308},{"Length":18,"Height":26,"Demand":1,"DemandMax":null,"Value":468}]}