{"Name":"C1_30_L_12","Objects":[{"Length":100,"Height":100,"Stock":null,"Cost":10000}],"Items":[{"Length":48,"Height":29,"Demand":8,"DemandMax":null,"Value":1392},{"Length":25,"Height":66,"Demand":4,"DemandMax":null,"Value":1650},{"Length":34,"Height":42,"Demand":3,"DemandMax":null,"Value":1428},{"Length":39,"Height":58,"Demand":2,"DemandMax":null,"Value":2262},{"Length":30,"Height":64,"Demand":3,"DemandMax":null,"Value":1920},{"Length":26,"Height":71,"Demand":2,"DemandMax":null,"Value":1846},{"Length":47,"Height":62,"Demand":2,"DemandMax":null,"Value":2914},{"Length":32,"Height":56,"Demand":3,"DemandMax":null,"Value":1792},{"Length":39,"Height":72,"Demand":1,"DemandMax":null,"Value":2808},{"Length":48,"Height":68,"Demand":1,"DemandMax":null,"Value":3264},{"Length":29,"Height":48,"Demand":5,"DemandMax":null,"Value":1392},{"Length":52,"Height":40,"Demand":2,"DemandMax":null,"Value":2080},{"Length":58,"Height":41,"Demand":1,"DemandMax":null,"Value":2378},{"Length":41,"Height":55,"Demand":2,"DemandMax":null,"Value":2255},{"Length":53,"Height":45,"Demand":2,"DemandMax":null,"Value":2385},{"Length":43,"Height":35,"Demand":3,"DemandMax":null,"Value":1505},{"Length":58,"Height":45,"Demand":2,"DemandMax":null,"Value":2610},{"Length":65,"Height":65,"Demand":1,"DemandMax":null,"Value":4225},{"Length":62,"Height":52,"Demand":1,"DemandMax":null,"Value":3224},{"Length":61,"Height":74,"Demand":1,"DemandMax":null,"Value":4514},{"Length":32,"Height":48,"Demand":6,"DemandMax":null,"Value":1536},{"Length":74,"Height":37,"Demand":1,"DemandMax":null,"Value":2738},{"Length":44,"Height":41,"Demand":3,"DemandMax":null,"Value":1804},{"Length":27,"Height":61,"Demand":3,"DemandMax":null,"Value":1647},{"Length":61,"Height":67,"Demand":1,"DemandMax":null,"Value":4087},{"Length":53,"Height":38,"Demand":2,"DemandMax":null,"Value":2014},{"Length":46,"Height":58,"Demand":2,"DemandMax":null,"Value":2668},{"Length":31,"Height":45,"Demand":5,"DemandMax":null,"Value":1395},{"Length":41,"Height":30,"Demand":1,"DemandMax":null,"Value":1230}]}