{"Name":"AH155","Objects":[{"Length":1000,"Height":42424,"Stock":null,"Cost":42424000}],"Items":[{"Length":358,"Height":366,"Demand":10,"DemandMax":null,"Value":131028},{"Length":328,"Height":364,"Demand":10,"DemandMax":null,"Value":119392},{"Length":309,"Height":373,"Demand":10,"DemandMax":null,"Value":115257},{"Length":323,"Height":354,"Demand":10,"DemandMax":null,"Value":114342},{"Length":296,"Height":375,"Demand":10,"DemandMax":null,"Value":111000},{"Length":285,"Height":371,"Demand":10,"DemandMax":null,"Value":105735},{"Length":342,"Height":308,"Demand":10,"DemandMax":null,"Value":105336},{"Length":277,"Height":353,"Demand":10,"DemandMax":null,"Value":97781},{"Length":336,"Height":276,"Demand":10,"DemandMax":null,"Value":92736},{"Length":247,"Height":372,"Demand":10,"DemandMax":null,"Value":91884},{"Length":297,"Height":301,"Demand":10,"DemandMax":null,"Value":89397},{"Length":282,"Height":311,"Demand":10,"DemandMax":null,"Value":87702},{"Length":260,"Height":337,"Demand":10,"DemandMax":null,"Value":87620},{"Length":309,"Height":279,"Demand":10,"DemandMax":null,"Value":86211},{"Length":222,"Height":362,"Demand":10,"DemandMax":null,"Value":80364},{"Length":307,"Height":251,"Demand":10,"DemandMax":null,"Value":77057},{"Length":263,"Height":287,"Demand":10,"DemandMax":null,"Value":75481},{"Length":306,"Height":232,"Demand":10,"DemandMax":null,"Value":70992},{"Length":242,"Height":291,"Demand":10,"DemandMax":null,"Value":70422},{"Length":207,"Height":338,"Demand":10,"DemandMax":null,"Value":69966},{"Length":311,"Height":223,"Demand":10,"DemandMax":null,"Value":69353},{"Length":187,"Height":365,"Demand":10,"DemandMax":null,"Value":68255},{"Length":315,"Height":201,"Demand":10,"DemandMax":null,"Value":63315},{"Length":351,"Height":178,"Demand":10,"DemandMax":null,"Value":62478},{"Length":179,"Height":346,"Demand":10,"DemandMax":null,"Value":61934},{"Length":166,"Height":373,"Demand":10,"DemandMax":null,"Value":61918},{"Length":165,"Height":362,"Demand":10,"DemandMax":null,"Value":59730},{"Length":272,"Height":217,"Demand":10,"DemandMax":null,"Value":59024},{"Length":222,"Height":240,"Demand":10,"DemandMax":null,"Value":53280},{"Length":234,"Height":226,"Demand":10,"DemandMax":null,"Value":52884},{"Length":203,"Height":247,"Demand":10,"DemandMax":null,"Value":50141},{"Length":288,"Height":171,"Demand":10,"DemandMax":null,"Value":49248},{"Length":175,"Height":278,"Demand":10,"DemandMax":null,"Value":48650},{"Length":151,"Height":320,"Demand":10,"DemandMax":null,"Value":48320},{"Length":251,"Height":191,"Demand":10,"DemandMax":null,"Value":47941},{"Length":311,"Height":154,"Demand":10,"DemandMax":null,"Value":47894},{"Length":166,"Height":288,"Demand":10,"DemandMax":null,"Value":47808},{"Length":320,"Height":145,"Demand":10,"DemandMax":null,"Value":46400},{"Length":355,"Height":127,"Demand":10,"DemandMax":null,"Value":45085},{"Length":259,"Height":168,"Demand":10,"DemandMax":null,"Value":43512},{"Length":366,"Height":116,"Demand":10,"DemandMax":null,"Value":42456},{"Length":191,"Height":220,"Demand":10,"DemandMax":null,"Value":42020},{"Length":123,"Height":337,"Demand":10,"DemandMax":null,"Value":41451},{"Length":179,"Height":230,"Demand":10,"DemandMax":null,"Value":41170},{"Length":291,"Height":128,"Demand":10,"DemandMax":null,"Value":37248},{"Length":186,"Height":192,"Demand":10,"DemandMax":null,"Value":35712},{"Length":179,"Height":199,"Demand":10,"DemandMax":null,"Value":35621},{"Length":334,"Height":104,"Demand":10,"DemandMax":null,"Value":34736},{"Length":118,"Height":289,"Demand":10,"DemandMax":null,"Value":34102},{"Length":317,"Height":107,"Demand":10,"DemandMax":null,"Value":33919},{"Length":157,"Height":214,"Demand":10,"DemandMax":null,"Value":33598},{"Length":236,"Height":142,"Demand":10,"DemandMax":null,"Value":33512},{"Length":181,"Height":179,"Demand":10,"DemandMax":null,"Value":32399},{"Length":113,"Height":283,"Demand":10,"DemandMax":null,"Value":31979},{"Length":91,"Height":346,"Demand":10,"DemandMax":null,"Value":31486},{"Length":151,"Height":206,"Demand":10,"DemandMax":null,"Value":31106},{"Length":143,"Height":203,"Demand":10,"DemandMax":null,"Value":29029},{"Length":122,"Height":218,"Demand":10,"DemandMax":null,"Value":26596},{"Length":306,"Height":86,"Demand":10,"DemandMax":null,"Value":26316},{"Length":313,"Height":84,"Demand":10,"DemandMax":null,"Value":26292},{"Length":252,"Height":104,"Demand":10,"DemandMax":null,"Value":26208},{"Length":155,"Height":169,"Demand":10,"DemandMax":null,"Value":26195},{"Length":89,"Height":286,"Demand":10,"DemandMax":null,"Value":25454},{"Length":357,"Height":69,"Demand":10,"DemandMax":null,"Value":24633},{"Length":167,"Height":146,"Demand":10,"DemandMax":null,"Value":24382},{"Length":87,"Height":280,"Demand":10,"DemandMax":null,"Value":24360},{"Length":179,"Height":129,"Demand":10,"DemandMax":null,"Value":23091},{"Length":135,"Height":167,"Demand":10,"DemandMax":null,"Value":22545},{"Length":240,"Height":92,"Demand":10,"DemandMax":null,"Value":22080},{"Length":79,"Height":277,"Demand":10,"DemandMax":null,"Value":21883},{"Length":145,"Height":150,"Demand":10,"DemandMax":null,"Value":21750},{"Length":113,"Height":178,"Demand":10,"DemandMax":null,"Value":20114},{"Length":73,"Height":270,"Demand":10,"DemandMax":null,"Value":19710},{"Length":180,"Height":106,"Demand":10,"DemandMax":null,"Value":19080},{"Length":264,"Height":69,"Demand":10,"DemandMax":null,"Value":18216},{"Length":106,"Height":164,"Demand":10,"DemandMax":null,"Value":17384},{"Length":184,"Height":93,"Demand":10,"DemandMax":null,"Value":17112},{"Length":76,"Height":218,"Demand":10,"DemandMax":null,"Value":16568},{"Length":229,"Height":68,"Demand":10,"DemandMax":null,"Value":15572},{"Length":110,"Height":138,"Demand":10,"DemandMax":null,"Value":15180},{"Length":76,"Height":176,"Demand":10,"DemandMax":null,"Value":13376},{"Length":59,"Height":219,"Demand":10,"DemandMax":null,"Value":12921},{"Length":103,"Height":119,"Demand":10,"DemandMax":null,"Value":12257},{"Length":135,"Height":90,"Demand":10,"DemandMax":null,"Value":12150},{"Length":51,"Height":228,"Demand":10,"DemandMax":null,"Value":11628},{"Length":148,"Height":77,"Demand":10,"DemandMax":null,"Value":11396},{"Length":113,"Height":99,"Demand":10,"DemandMax":null,"Value":11187},{"Length":37,"Height":290,"Demand":10,"DemandMax":null,"Value":10730},{"Length":96,"Height":106,"Demand":10,"DemandMax":null,"Value":10176},{"Length":102,"Height":99,"Demand":10,"DemandMax":null,"Value":10098},{"Length":204,"Height":38,"Demand":10,"DemandMax":null,"Value":7752},{"Length":180,"Height":43,"Demand":10,"DemandMax":null,"Value":7740},{"Length":107,"Height":71,"Demand":10,"DemandMax":null,"Value":7597},{"Length":47,"Height":152,"Demand":10,"DemandMax":null,"Value":7144},{"Length":86,"Height":69,"Demand":10,"DemandMax":null,"Value":5934},{"Length":92,"Height":50,"Demand":10,"DemandMax":null,"Value":4600},{"Length":160,"Height":28,"Demand":10,"DemandMax":null,"Value":4480},{"Length":80,"Height":55,"Demand":10,"DemandMax":null,"Value":4400},{"Length":52,"Height":81,"Demand":10,"DemandMax":null,"Value":4212},{"Length":25,"Height":136,"Demand":10,"DemandMax":null,"Value":3400}]}