{"Name":"AH158","Objects":[{"Length":1000,"Height":39901,"Stock":null,"Cost":39901000}],"Items":[{"Length":361,"Height":373,"Demand":10,"DemandMax":null,"Value":134653},{"Length":362,"Height":338,"Demand":10,"DemandMax":null,"Value":122356},{"Length":371,"Height":319,"Demand":10,"DemandMax":null,"Value":118349},{"Length":315,"Height":365,"Demand":10,"DemandMax":null,"Value":114975},{"Length":333,"Height":337,"Demand":10,"DemandMax":null,"Value":112221},{"Length":330,"Height":336,"Demand":10,"DemandMax":null,"Value":110880},{"Length":315,"Height":326,"Demand":10,"DemandMax":null,"Value":102690},{"Length":297,"Height":298,"Demand":10,"DemandMax":null,"Value":88506},{"Length":336,"Height":262,"Demand":10,"DemandMax":null,"Value":88032},{"Length":370,"Height":229,"Demand":10,"DemandMax":null,"Value":84730},{"Length":255,"Height":323,"Demand":10,"DemandMax":null,"Value":82365},{"Length":285,"Height":289,"Demand":10,"DemandMax":null,"Value":82365},{"Length":327,"Height":238,"Demand":10,"DemandMax":null,"Value":77826},{"Length":217,"Height":348,"Demand":10,"DemandMax":null,"Value":75516},{"Length":366,"Height":188,"Demand":10,"DemandMax":null,"Value":68808},{"Length":301,"Height":228,"Demand":10,"DemandMax":null,"Value":68628},{"Length":248,"Height":263,"Demand":10,"DemandMax":null,"Value":65224},{"Length":173,"Height":375,"Demand":10,"DemandMax":null,"Value":64875},{"Length":184,"Height":340,"Demand":10,"DemandMax":null,"Value":62560},{"Length":214,"Height":289,"Demand":10,"DemandMax":null,"Value":61846},{"Length":214,"Height":279,"Demand":10,"DemandMax":null,"Value":59706},{"Length":295,"Height":201,"Demand":10,"DemandMax":null,"Value":59295},{"Length":166,"Height":332,"Demand":10,"DemandMax":null,"Value":55112},{"Length":334,"Height":165,"Demand":10,"DemandMax":null,"Value":55110},{"Length":298,"Height":184,"Demand":10,"DemandMax":null,"Value":54832},{"Length":216,"Height":246,"Demand":10,"DemandMax":null,"Value":53136},{"Length":330,"Height":159,"Demand":10,"DemandMax":null,"Value":52470},{"Length":136,"Height":370,"Demand":10,"DemandMax":null,"Value":50320},{"Length":226,"Height":221,"Demand":10,"DemandMax":null,"Value":49946},{"Length":149,"Height":332,"Demand":10,"DemandMax":null,"Value":49468},{"Length":254,"Height":194,"Demand":10,"DemandMax":null,"Value":49276},{"Length":312,"Height":152,"Demand":10,"DemandMax":null,"Value":47424},{"Length":192,"Height":247,"Demand":10,"DemandMax":null,"Value":47424},{"Length":316,"Height":149,"Demand":10,"DemandMax":null,"Value":47084},{"Length":284,"Height":165,"Demand":10,"DemandMax":null,"Value":46860},{"Length":183,"Height":250,"Demand":10,"DemandMax":null,"Value":45750},{"Length":156,"Height":292,"Demand":10,"DemandMax":null,"Value":45552},{"Length":189,"Height":236,"Demand":10,"DemandMax":null,"Value":44604},{"Length":168,"Height":262,"Demand":10,"DemandMax":null,"Value":44016},{"Length":122,"Height":357,"Demand":10,"DemandMax":null,"Value":43554},{"Length":262,"Height":166,"Demand":10,"DemandMax":null,"Value":43492},{"Length":122,"Height":320,"Demand":10,"DemandMax":null,"Value":39040},{"Length":211,"Height":184,"Demand":10,"DemandMax":null,"Value":38824},{"Length":149,"Height":254,"Demand":10,"DemandMax":null,"Value":37846},{"Length":150,"Height":252,"Demand":10,"DemandMax":null,"Value":37800},{"Length":262,"Height":143,"Demand":10,"DemandMax":null,"Value":37466},{"Length":332,"Height":112,"Demand":10,"DemandMax":null,"Value":37184},{"Length":359,"Height":102,"Demand":10,"DemandMax":null,"Value":36618},{"Length":318,"Height":115,"Demand":10,"DemandMax":null,"Value":36570},{"Length":292,"Height":125,"Demand":10,"DemandMax":null,"Value":36500},{"Length":187,"Height":181,"Demand":10,"DemandMax":null,"Value":33847},{"Length":184,"Height":183,"Demand":10,"DemandMax":null,"Value":33672},{"Length":284,"Height":116,"Demand":10,"DemandMax":null,"Value":32944},{"Length":187,"Height":173,"Demand":10,"DemandMax":null,"Value":32351},{"Length":183,"Height":176,"Demand":10,"DemandMax":null,"Value":32208},{"Length":120,"Height":264,"Demand":10,"DemandMax":null,"Value":31680},{"Length":131,"Height":218,"Demand":10,"DemandMax":null,"Value":28558},{"Length":245,"Height":113,"Demand":10,"DemandMax":null,"Value":27685},{"Length":81,"Height":337,"Demand":10,"DemandMax":null,"Value":27297},{"Length":76,"Height":353,"Demand":10,"DemandMax":null,"Value":26828},{"Length":79,"Height":330,"Demand":10,"DemandMax":null,"Value":26070},{"Length":122,"Height":213,"Demand":10,"DemandMax":null,"Value":25986},{"Length":128,"Height":191,"Demand":10,"DemandMax":null,"Value":24448},{"Length":204,"Height":119,"Demand":10,"DemandMax":null,"Value":24276},{"Length":141,"Height":162,"Demand":10,"DemandMax":null,"Value":22842},{"Length":80,"Height":256,"Demand":10,"DemandMax":null,"Value":20480},{"Length":353,"Height":56,"Demand":10,"DemandMax":null,"Value":19768},{"Length":73,"Height":257,"Demand":10,"DemandMax":null,"Value":18761},{"Length":375,"Height":49,"Demand":10,"DemandMax":null,"Value":18375},{"Length":122,"Height":150,"Demand":10,"DemandMax":null,"Value":18300},{"Length":51,"Height":348,"Demand":10,"DemandMax":null,"Value":17748},{"Length":85,"Height":206,"Demand":10,"DemandMax":null,"Value":17510},{"Length":187,"Height":83,"Demand":10,"DemandMax":null,"Value":15521},{"Length":110,"Height":135,"Demand":10,"DemandMax":null,"Value":14850},{"Length":51,"Height":280,"Demand":10,"DemandMax":null,"Value":14280},{"Length":49,"Height":288,"Demand":10,"DemandMax":null,"Value":14112},{"Length":269,"Height":52,"Demand":10,"DemandMax":null,"Value":13988},{"Length":358,"Height":39,"Demand":10,"DemandMax":null,"Value":13962},{"Length":245,"Height":55,"Demand":10,"DemandMax":null,"Value":13475},{"Length":39,"Height":308,"Demand":10,"DemandMax":null,"Value":12012},{"Length":64,"Height":174,"Demand":10,"DemandMax":null,"Value":11136},{"Length":188,"Height":59,"Demand":10,"DemandMax":null,"Value":11092},{"Length":296,"Height":37,"Demand":10,"DemandMax":null,"Value":10952},{"Length":97,"Height":111,"Demand":10,"DemandMax":null,"Value":10767},{"Length":122,"Height":88,"Demand":10,"DemandMax":null,"Value":10736},{"Length":78,"Height":133,"Demand":10,"DemandMax":null,"Value":10374},{"Length":44,"Height":225,"Demand":10,"DemandMax":null,"Value":9900},{"Length":176,"Height":54,"Demand":10,"DemandMax":null,"Value":9504},{"Length":195,"Height":44,"Demand":10,"DemandMax":null,"Value":8580},{"Length":58,"Height":142,"Demand":10,"DemandMax":null,"Value":8236},{"Length":52,"Height":149,"Demand":10,"DemandMax":null,"Value":7748},{"Length":90,"Height":82,"Demand":10,"DemandMax":null,"Value":7380},{"Length":231,"Height":27,"Demand":10,"DemandMax":null,"Value":6237},{"Length":58,"Height":100,"Demand":10,"DemandMax":null,"Value":5800},{"Length":55,"Height":92,"Demand":10,"DemandMax":null,"Value":5060},{"Length":37,"Height":97,"Demand":10,"DemandMax":null,"Value":3589},{"Length":46,"Height":64,"Demand":10,"DemandMax":null,"Value":2944},{"Length":46,"Height":54,"Demand":10,"DemandMax":null,"Value":2484},{"Length":84,"Height":27,"Demand":10,"DemandMax":null,"Value":2268},{"Length":44,"Height":39,"Demand":10,"DemandMax":null,"Value":1716}]}